Workbook

Sheet Calculo Informes
B1: Periodo Informe Mensual
B2: Fecha Inicio Periodo | C2: 46091
B3: Fecha Termino Periodo | C3: 46121
B5: Grupo | C5: INC | D5: Warning | E5: REQ | F5: Total por Equipo
B6: Middleware | C6: =SUM(COUNTIFS(OscarMora!$B$2:$B$10001,">="&C2,OscarMora!$B$2:$B$10001,"<="&C3,OscarMora!$F$2:$F$10001,"=INC"), COUNTIFS(AmericoSaravia!$B$2:$B$10072,">="&C2,AmericoSaravia!$B$2:$B$10072,"<="&C3,AmericoSaravia!$F$2:$F$10072,"=INC"), COUNTIFS(GabrielNuñez!$B$2:$B$9983,">="&C2,GabrielNuñez!$B$2:$B$9983,"<="&C3,GabrielNuñez!$F$2:$F$9983,"=INC")) -> 0 | D6: =SUM(COUNTIFS(OscarMora!$B$2:$B$10001,">="&C2,OscarMora!$B$2:$B$10001,"<="&C3,OscarMora!$F$2:$F$10001,"=WARNING"),COUNTIFS(AmericoSaravia!$B$2:$B$10072,">="&C2,AmericoSaravia!$B$2:$B$10072,"<="&C3,AmericoSaravia!$F$2:$F$10072,"=WARNING"),COUNTIFS(GabrielNuñez!$B$2:$B$9983,">="&C2,GabrielNuñez!$B$2:$B$9983,"<="&C3,GabrielNuñez!$F$2:$F$9983,"=WARNING")) -> 3 | E6: =SUM(COUNTIFS(OscarMora!$B$2:$B$10001,">="&C2,OscarMora!$B$2:$B$10001,"<="&C3,OscarMora!$F$2:$F$10001,"=REQ"),COUNTIFS(AmericoSaravia!$B$2:$B$10072,">="&C2,AmericoSaravia!$B$2:$B$10072,"<="&C3,AmericoSaravia!$F$2:$F$10072,"=REQ"),COUNTIFS(GabrielNuñez!$B$2:$B$9983,">="&C2,GabrielNuñez!$B$2:$B$9983,"<="&C3,GabrielNuñez!$F$2:$F$9983,"=REQ")) -> 215 | F6: =SUM(C6:E6) -> 218
B7: Administración Nube | C7: =SUM(COUNTIFS(GonzaloRodriguez!$B$2:$B$9988,">="&C2,GonzaloRodriguez!$B$2:$B$9988,"<="&C3,GonzaloRodriguez!$F$2:$F$9988,"=INC"),COUNTIFS(CesarGonzalez!$B$2:$B$10000,">="&C2,CesarGonzalez!$B$2:$B$10000,"<="&C3,CesarGonzalez!$F$2:$F$10000,"=INC")) -> 0 | D7: =SUM(COUNTIFS(GonzaloRodriguez!$B$2:$B$9988,">="&C2,GonzaloRodriguez!$B$2:$B$9988,"<="&C3,GonzaloRodriguez!$F$2:$F$9988,"=WARNING"),COUNTIFS(CesarGonzalez!$B$2:$B$10000,">="&C2,CesarGonzalez!$B$2:$B$10000,"<="&C3,CesarGonzalez!$F$2:$F$10000,"=WARNING")) -> 0 | E7: =SUM(COUNTIFS(GonzaloRodriguez!$B$2:$B$9988,">="&C2,GonzaloRodriguez!$B$2:$B$9988,"<="&C3,GonzaloRodriguez!$F$2:$F$9988,"=REQ"),COUNTIFS(CesarGonzalez!$B$2:$B$10000,">="&C2,CesarGonzalez!$B$2:$B$10000,"<="&C3,CesarGonzalez!$F$2:$F$10000,"=REQ")) -> 61 | F7: =SUM(C7:E7) -> 61
B8: Administración SO, Servidores y Dominios | C8: =SUM(COUNTIFS(RodrigoLorca!$B$2:$B$10000,">="&C2,RodrigoLorca!$B$2:$B$10000,"<="&C3,RodrigoLorca!$F$2:$F$10000,"=INC"),COUNTIFS(PabloSalazar!$B$2:$B$10000,">="&C2,PabloSalazar!$B$2:$B$10000,"<="&C3,PabloSalazar!$F$2:$F$10000,"=INC")) -> 0 | D8: =SUM(COUNTIFS(RodrigoLorca!$B$2:$B$10000,">="&C2,RodrigoLorca!$B$2:$B$10000,"<="&C3,RodrigoLorca!$F$2:$F$10000,"=WARNING"),COUNTIFS(PabloSalazar!$B$2:$B$10000,">="&C2,PabloSalazar!$B$2:$B$10000,"<="&C3,PabloSalazar!$F$2:$F$10000,"=WARNING")) -> 8 | E8: =SUM(COUNTIFS(RodrigoLorca!$B$2:$B$10000,">="&C2,RodrigoLorca!$B$2:$B$10000,"<="&C3,RodrigoLorca!$F$2:$F$10000,"=REQ"),COUNTIFS(PabloSalazar!$B$2:$B$10000,">="&C2,PabloSalazar!$B$2:$B$10000,"<="&C3,PabloSalazar!$F$2:$F$10000,"=REQ")) -> 44 | F8: =SUM(C8:E8) -> 52
B9: Monitoreo y Respaldo | C9: =SUM(COUNTIFS(CarlosJara!$B$2:$B$10006,">="&C2,CarlosJara!$B$2:$B$10006,"<="&C3,CarlosJara!$F$2:$F$10006,"=INC"),COUNTIFS(JPBuzeta!$B$2:$B$10010,">="&C2,JPBuzeta!$B$2:$B$10010,"<="&C3,JPBuzeta!$F$2:$F$10010,"=INC"),COUNTIFS(CristiánVásquez!$B$2:$B$9992,">="&C2,CristiánVásquez!$B$2:$B$9992,"<="&C3,CristiánVásquez!$F$2:$F$9992,"=INC"),COUNTIFS(AlejandroIpinza!$B$2:$B$10000,">="&C2,AlejandroIpinza!$B$2:$B$10000,"<="&C3,AlejandroIpinza!$F$2:$F$10000,"=INC")) -> 1 | D9: =SUM(COUNTIFS(CarlosJara!$B$2:$B$10006,">="&C2,CarlosJara!$B$2:$B$10006,"<="&C3,CarlosJara!$F$2:$F$10006,"=WARNING"),COUNTIFS(JPBuzeta!$B$2:$B$10010,">="&C2,JPBuzeta!$B$2:$B$10010,"<="&C3,JPBuzeta!$F$2:$F$10010,"=WARNING"),COUNTIFS(CristiánVásquez!$B$2:$B$9992,">="&C2,CristiánVásquez!$B$2:$B$9992,"<="&C3,CristiánVásquez!$F$2:$F$9992,"=WARNING"), COUNTIFS(AlejandroIpinza!$B$2:$B$10000,">="&C2,AlejandroIpinza!$B$2:$B$10000,"<="&C3,AlejandroIpinza!$F$2:$F$10000,"=WARNING")) -> 14 | E9: =SUM(COUNTIFS(CarlosJara!$B$2:$B$10006,">="&C2,CarlosJara!$B$2:$B$10006,"<="&C3,CarlosJara!$F$2:$F$10006,"=REQ"),COUNTIFS(JPBuzeta!$B$2:$B$10010,">="&C2,JPBuzeta!$B$2:$B$10010,"<="&C3,JPBuzeta!$F$2:$F$10010,"=REQ"),COUNTIFS(CristiánVásquez!$B$2:$B$9992,">="&C2,CristiánVásquez!$B$2:$B$9992,"<="&C3,CristiánVásquez!$F$2:$F$9992,"=REQ"),COUNTIFS(AlejandroIpinza!$B$2:$B$10000,">="&C2,AlejandroIpinza!$B$2:$B$10000,"<="&C3,AlejandroIpinza!$F$2:$F$10000,"=REQ")) -> 224 | F9: =SUM(C9:E9) -> 239
B11: Total Incidentes | C11: =SUM(C6:C9) -> 1
B12: Total Warning | C12: =SUM(D6:D9) -> 25
B13: Total Requerimientos | C13: =SUM(E6:E9) -> 544
B14: Total General | C14: =SUM(C11:C13) -> 570

Sheet CesarGonzalez
B1: FECHA SOLICITUD | C1: Periodo | D1: AREA / PERSONAL SOLICITANTE | E1: PROFESIONAL | F1: INC / REQ / WARNING | G1: Actividad | H1: Detalle / Observación | I1: Estado (en proceso, pendiente, finalizado) | J1: Tiempo estimado actividad
B2: 45737 | C2: 45723 | D2: Chileatiende | E2: Cesar Gonzalez | F2: REQ | G2: Ticket N° 14347 - URGENTE!!! Solicitud de actualización minisitio ipsenlinea :: Bajada servicio SIAGF en SUSESO | H2: Actualizar el minisitio de ipsenlinea (https://www.ipsenlinea.cl/) producto de la bajada del servicio SIAGF por parte de SUSESO, lo cual afecta al trámite reconocimiento de carga familiar y maternal.
B3: 45741 | C3: 45724 | D3: Chileatiende | E3: Cesar Gonzalez | F3: REQ | G3: Rollback de actualización minisitio ipsenlinea :: Bajada servicio SIAGF en SUSESO | H3: Se realiza rollback de actualizacion de minisitio requerido por Chileatiende durante las fechas 21/03 al 24/03 - Este cambio se realiza fuera de horario debido a que el sitio debia estar disponbile a primera hora del dia Martes 25/03
B4: 45741 | C4: 45725 | D4: Operaciones IPS | E4: Cesar Gonzalez | F4: REQ | G4: Seguimiento: [IPS] Temas Pendientes - Cloud Services ☁ | H4: Call a realizar todos los dias Martes a partir de las 9:30 Hrs - Se revisan temas pendientes y proyectos en curso correspondientes a Cloud Services IPS.
B5: 45742 | C5: 45726 | D5: Daniel Zamora Operaciones IPS | E5: Cesar Gonzalez | F5: REQ | G5: Ticket N° 14380 - Apagado Nodos 5-6 Proyecto AFPER | H5: Se realiza apagado de instancias AFPER-Consulta 5-6 correspondientes al proyecto AFPER solicitados por Daniel Zamora, realizada el drenaje respectivo en los balanceadores pertinentes.
B6: 45742 | C6: 45727 | D6: Operaciones IPS | E6: Cesar Gonzalez | F6: REQ | G6: Continuacion Seguimiento: [IPS] Temas Pendientes - Cloud Services ☁ | H6: Se continua call en donde se revisan temas pendientes y proyectos en curso correspondientes a Cloud Services IPS.
B7: 45743 | C7: 45728 | D7: Miguel Garrido - Abenis | E7: Cesar Gonzalez | F7: REQ | G7: Coordinación ABENIS - IPS | H7: Call de coordinacion
B8: 45743 | C8: 45729 | D8: Victor Bustos - IPS | E8: Cesar Gonzalez | F8: REQ | G8: Ticket N° 14393 - Encendido Instancias DEV AFPER | H8: Solicitan el encendido de instancias AFPER DEV en horario habil.
B9: 45743 | C9: 45730 | D9: Daniel Zamora Operaciones IPS | E9: Cesar Gonzalez | F9: REQ | G9: Call Presentacion De Estrategia Abenis | H9: Call de presentacion de estrategia y planificacion Abenis-IPS
B10: 45744 | C10: 45731 | D10: IPS-TIVIT | E10: Cesar Gonzalez | F10: REQ | G10: Call Seguimiento De Contrato MS Azure | H10: Call con TAM TIVIT y Daniel Zamora IPS para la estrategia de implementacion y configuracion del servicio PaaS Azure DevOps.
B11: 45744 | C11: 45732 | D11: Area SAP IPS - Area Operaciones IPS | E11: Cesar Gonzalez | F11: REQ | G11: Actividad Planificada - Fuera De Horario: Upgrade de S.O RHEL 8.10 en SAP HANA DB (10.88.1.135) 🗄️🗃️ | H11: Actividad planificada - fuera de horario con areas de SAP y Operaciones IPS, correspondiente al Upgrade de S.O para ambiente SAP HANA BD (10.88.1.135)
B12: 45747 | C12: 45733 | D12: Ricardo Orellana DBA IPS | E12: Cesar Gonzalez | F12: REQ | G12: Apoyo - Autorización del acceso de base de datos a SQL Database, Instancia administrada de SQL | H12: Se realizan las validaciones y verificacion de los usuarios dbamanager ya que actualmente Ricardo Orellana no tiene acceso a BD PaaS PROD con usuario administrador.
B13: 45748 | C13: 45748 | D13: Daniel Zamora Operaciones IPS | E13: Cesar Gonzalez | F13: REQ | G13: Continuacion Call Presentacion De Estrategia Abenis | H13: Usuario Christian Fuentes - Area DyM IPS requiere archivo de configuracion aplication.properties para el servicio App Services Garantia Estatal.
B14: 45748 | D14: Christian Fuentes IPS | E14: Cesar Gonzalez | F14: REQ | G14: Ticket N° 14459 - Solicitud Archivo De Configuracion App Services Garantia Estatal | H14: Usuario Angel Alvarez de Area Ciberseguridad IPS requiere lso certificados renovados wildcard para los dominios inp.cl e ips.gob.cl ya que estan proximos a expirar (11/04/25) Seran enviados y adjuntos en ticket creado.
B15: 45748 | D15: Angel Alvarez IPS | E15: Cesar Gonzalez | F15: REQ | G15: Ticket N° 14462 - Solicitud certificados wildcard inp.cl e ips.gob.cl | H15: Usuario: Gonzalo Sepulvedad solicita deshabilitar Scheduler de Apagado correspondiente al ambiente UAT PDP con fecha 02/04 hasta 04/04 volviendo nuevamente habilitar el Scheduler.
B16: 45749 | D16: Gonzalo Sepulveda IPS | E16: Cesar Gonzalez | F16: REQ | G16: Ticket N° 14479 - Deshabilitar Scheduler Apagado Ambientes UAT PDP | H16: Se coordina call con TAM Jorge Quiroz de TIVIT y Daniel Zamora IPS para realizar el proceso de habilitacion de suscripcion de servicios PaaS Azure DevOps requeridos por IPS.
B17: 45750 | D17: Jorge Quiroz - TIVIT Daniel Zamora - IPS | E17: Cesar Gonzalez | F17: REQ | G17: Call Cuenta y Suscripcion Servicios PaaS Azure DevOps | H17: Call semanal en donde se revisan temas pendientes y proyectos en curso correspondientes a Cloud Services IPS.
B18: 45750 | D18: Operaciones IPS | E18: Cesar Gonzalez | F18: REQ | G18: Call Seguimiento: [IPS] Temas Pendientes - Cloud Services ☁ | H18: Se coordina actividad para realizar fuera de horario correspondiente al proceso de remediacion de vulnerabilidades detectadas en instancias AWS/Azure por nuestra area de Ciberseguridad. Para esta actividad se realizara la remediacion de 4 instancias Azure y 2 instancias AWS.
B19: 45750 | D19: Operaciones IPS | E19: Cesar Gonzalez | F19: REQ | G19: Fuera De Horario - Actividad de Remediación de Vulnerabilidades | H19: Se gestiona call con usuario Ricardo Orellana debido a problemas con usuarios con rol dbamanager creados en recursos Azure SQL
B20: 45750 | D20: Ricardo Orellana DBA IPS | E20: Cesar Gonzalez | F20: REQ | G20: Call Revision Acceso Azure SQL | H20: Se gestiona call para revisar problemas con servicios Weblogics, debido a una actualizacion realizad ay reportada por nuestra area de Ciberseguridad IPS, el cual se realiza actualizacion del servicio PrimeFaces a version 11
B21: 45751 | D21: Equipo Middleware IPS | E21: Cesar Gonzalez | F21: REQ | G21: Call Validacion De Servicios WLSPROD03-WLSPROD04 | H21: Se gestiona call correspondiente a la planificacion y coordinacion de trabajos para las actividades de cambio de hora.
B22: 45751 | D22: Operaciones IPS | E22: Cesar Gonzalez | F22: REQ | G22: Call Planificacion Cambio De Hora - Invierno 2025 | H22: Se gestiona actividad planificada fuera de horario, en conjunto con area Servicios Oracle IPS para realizar mantenicon y reparacion de isntancia WebLogic WLSProd03 ya que presento problemas en su actualizacion de repositoris Pramefaces solcitado como mitigacion por el area de Ciberseguridad.
B23: 45754 | D23: Servicios Oracle IPS | E23: Cesar Gonzalez | F23: REQ | G23: Actividad Planificada - Fuera De Horario: Apoyo Mantencion y Configuracion Instancia Weblogic - WLSPROD03 AWS | H23: Call semanal en donde se revisan temas pendientes y proyectos en curso correspondientes a Cloud Services IPS.
B24: 45755 | D24: Operaciones IPS | E24: Cesar Gonzalez | F24: REQ | G24: Call Seguimiento: [IPS] Temas Pendientes - Cloud Services ☁ | H24: Se procede con la eliminacion de Snapshots obtenidos en el proceso de mitigacion de vulnerabilidades ya resueltos en los sistemas de Azure.
B25: 45756 | D25: Operaciones IPS | E25: Cesar Gonzalez | F25: REQ | G25: AZ IPS - Eliminar RG Snapshots Remediacion | H25: Se realiza call con DBA Ricardo Orellana para explicar la situacion del proyecto AlwaysOn SQLent y detalles del proceso de migracion del servicio de LB que actualmente utiliza, ya que MS Azure descontinuara los servicios de LB Classic el 30/09/25
... B36: 45764 | D36: Area Ciberseguridad IPS Operaciones IPS | E36: Cesar Gonzalez | F36: REQ | G36: Call Revision FW AWS/Azure | H36: Se coordina call para definir las estrategias de implementacion de FW PAN en los servicios Cloud actuales que contiene IPS.
B37: 45765 | D37: FERIADO | E37: Cesar Gonzalez | F37: REQ | G37: Feriado
B38: 45768 | D38: Area Operaciones CHA-IPS Morris Opazo | E38: Cesar Gonzalez | F38: REQ | G38: Call CHA - Modernizacion a AWS | H38: Se realiza call para revisar procesos de modernizacion de apps por obselecencia actual en CHA e IPS
B39: 45769 | D39: Area Ciberseguridad IPS | E39: Cesar Gonzalez | F39: REQ | G39: Ticket N° 14684 - Hallazgos ANCI - ipsenlinea | H39: Se genera ticket debido a los hallazgos de seguridad obtenidos para el servicio persona.ipsenlinea.cl
B40: 45770 | D40: IPS - TIVIT - CHA - AWS | E40: Cesar Gonzalez | F40: REQ | G40: [EXTERNO]RV: IPS / AWS / Tivit Kickoff Proyecto Fase 2-Implementación de Landing Zone, Adecuación de Cuentas AWS y Epicas de Seguridad | H40: Se cita a kick off migración LZ de IPS - Reunion en oficinas de IPS
B41: 45770 | D41: IPS | E41: Cesar Gonzalez | F41: REQ | G41: FinOps Azure IPS | H41: Reunion para revisar estrategias FinOps en ambiente Azure.
B42: 45770 | D42: Gonzalo Sepulveda IPS | E42: Cesar Gonzalez | F42: REQ | G42: Ticket N° 14707 - Apagado PDP QA | H42: Solicitud de encendido de ambientes PDP QA para la fecha indicada
B43: 45771 | D43: Palo Alto Ciberseguridad IPS Operaciones IPS | E43: Cesar Gonzalez | F43: REQ | G43: Call Implmentacion FW PAN - Cuentas AWS IPS | H43: Call para verificar las formas de implementacion de FW PAN en cuentas AWS IPS
B44: 45775 | D44: TIVIT - Operaciones IPS | E44: Cesar Gonzalez | F44: REQ | G44: Call Implementacion y planificacion - Puesta en Marcha Azure DevOps | H44: Call para revisar y planificar la puesta en marcha y estrategia del servicio Azure DevOps para IPS
B45: 45775 | D45: Sergio Santibañez | E45: Cesar Gonzalez | F45: REQ | G45: Ticket N° 14735 - Encendidos Instancias AFPER UAT | H45: Ticket para realizar el encendido de ambientes UAT AFPER
B46: 45775 | D46: Operaciones IPS | E46: Cesar Gonzalez | F46: REQ | G46: Call Seguimiento: [IPS] Temas Pendientes - Cloud Services ☁ | H46: Call semanal en donde se revisan temas pendientes y proyectos en curso correspondientes a Cloud Services IPS.
B47: 45775 | D47: Gonzalo Sepulveda IPS | E47: Cesar Gonzalez | F47: REQ | G47: Ticket N° 14752 - Apagados DEV PDP | H47: Ticket para no realizar el apagado de isntancias PDP DEV durante esta fecha.
B48: 45777 | D48: TIVIT - Operaciones IPS | E48: Cesar Gonzalez | F48: REQ | G48: Call IPS: revision Ticket R95489 | H48: Call de revision de ticket
B49: 45777 | D49: Area Operaciones y NOC IPS | E49: Cesar Gonzalez | F49: REQ | G49: Call Monitoreo - Coordinación Programación Encendido/Apagado Instancias | H49: Call de revision correspondiente al procedimiento de encendidos y apagados de instancias solcitados y reportar al NOC correspondiente.
B50: 45779 | C50: 45778 | D50: Ciberseguridad Operaciones IPS | E50: Cesar Gonzalez | F50: REQ | G50: Ticket N°: 14776 - Evento De Seguridad | H50: Se gestiona ticket por parte de nuestra area de Ciberseguridad por eventos de seguridad detectados en AWS.
B51: 45779 | D51: Gonzalo Sepulveda IPS | E51: Cesar Gonzalez | F51: REQ | G51: Ticket N°: 14783 - Apagado Instancias PDP Dev | H51: Se gestiona ticket para no realizar el apagado de instancias DEV PDP
B52: 45779 | D52: Area De Ciberseguridad | E52: Cesar Gonzalez | F52: REQ | G52: Ticket N°: 14786 - Evento De Seguridad IPS | H52: Se gestiona ticket por parte de nuestra area de Ciberseguridad por eventos de seguridad detectados en AWS.
B53: 45782 | D53: Palo Alto Ciberseguridad IPS Operaciones IPS | E53: Cesar Gonzalez | F53: REQ | G53: Continuacion - Call Implmentacion FW PAN - Cuentas AWS IPS | H53: Call para verificar las formas de implementacion de FW PAN en cuentas AWS IPS
B54: 45783 | D54: MAFIPS | E54: Cesar Gonzalez | F54: REQ | G54: Ticket N° 14791 - Estado Repositorio Documental | 05-05-2025 | H54: Verificar disponiblidad de repositorio S3
B55: 45783 | D55: Gonzalo Sepulveda IPS | E55: Cesar Gonzalez | F55: REQ | G55: Ticket N°: 14819 - Apagado Instancias PDP Dev | H55: Se gestiona ticket para no realizar el apagado de instancias DEV PDP
B56: 45784 | D56: Gonzalo Sepulveda IPS | E56: Cesar Gonzalez | F56: REQ | G56: Ticket N°: 14833 - Apagado Instancias PDP SIT | H56: Se gestiona ticket para no realizar el apagado de instancias SIT PDP
B57: 45785 | D57: Area Ciberseguridad | E57: Cesar Gonzalez | F57: REQ | G57: Call Mitigación de Vulnerabilidades Informadas x Prisma | H57: Se gestiona call para revisar alternativas de mitigacion de vulnerabilidades en ambientes IPS
B58: 45785 | D58: Operaciones IPS | E58: Cesar Gonzalez | F58: REQ | G58: Call Seguimiento: [IPS] Temas Pendientes - Cloud Services ☁ | H58: Call semanal en donde se revisan temas pendientes y proyectos en curso correspondientes a Cloud Services IPS.
B59: 45786 | D59: Area Proyectos | E59: Cesar Gonzalez | F59: REQ | G59: Call Expediente Electronico - Validacion Ethical Hacking | H59: Call para verificar el servicio Expediente Electronico debido a que se encuentra expuesto a internet, se realizao un Ethical Hacking actual al servicio.
B60: 45786 | D60: Andres Bastidas - Area Proyectos - Area Ciberseguridad | E60: Cesar Gonzalez | F60: REQ | G60: Call Problemas App Service sdmback-dev - Conexión Consecio DEV | H60: Call para verificar el servicio sdmback-dev hacia BD Concesio-DEV
B61: 45786 | D61: Area Ciberseguridad | E61: Cesar Gonzalez | F61: REQ | G61: Ticket N° 14847 - 14846 - Eventos de Seguridad IPS | H61: Ticket para realizar las verificaciones y mitigaciones reportadas por Ciberseguridad.
B62: 45789 | D62: TIVIT - Operaciones IPS | E62: Cesar Gonzalez | F62: REQ | G62: Call Solicitud PoC Azure DevOps IPS | H62: Call para coordina ry planificar PoC asociados a los servicios de Azure DevOps para IPS
... B66: 45790 | D66: TIVIT - Operaciones IPS - AWS | E66: Cesar Gonzalez | F66: REQ | G66: Call Fase II - Launch Ready Planning AWS | H66: Call para gestionar proceso de inicializacion del proyecto AWS Adecuacion de cuentas
B67: 45791 | D67: TIVIT - Operaciones IPS - AWS | E67: Cesar Gonzalez | F67: REQ | G67: Call Fase II - Launch Ready Planning AWS - Segunda Parte
B68: 45792 | D68: Area Ciberseguridad | E68: Cesar Gonzalez | F68: REQ | G68: Ticket N° 14931 - Eventos de Seguridad IPS | H68: Ticket para realizar las verificaciones y mitigaciones reportadas por Ciberseguridad.
B69: 45792 | D69: TIVIT - Operaciones IPS - AWS | E69: Cesar Gonzalez | F69: REQ | G69: Call Fase II Sprint 1 | H69: Continuacion - Call para gestionar proceso de inicializacion del proyecto AWS Adecuacion de cuentas
B70: 45792 | D70: Operaciones IPS | E70: Cesar Gonzalez | F70: REQ | G70: Call TLS 1.2 Estado De Servicios Internos | H70: Se realiza call para realizar las validaciones de los servicios TLS 1.2 y verificar los servicios internos de IPS.
B71: 45793 | D71: TIVIT - Operaciones IPS - AWS | E71: Cesar Gonzalez | F71: REQ | G71: Call IPS Fase II - Daily AWS-TIVIT | H71: Continuacion - Call para gestionar proceso de inicializacion del proyecto AWS Adecuacion de cuentas
B72: 45793 | D72: Area Ciberseguridad | E72: Cesar Gonzalez | F72: REQ | G72: Ticket N° 14951 - Eventos de Seguridad IPS | H72: Ticket para realizar las verificaciones y mitigaciones reportadas por Ciberseguridad.
B73: 45796 | D73: TIVIT - Operaciones IPS - AWS | E73: Cesar Gonzalez | F73: REQ | G73: Call IPS Fase II - Daily AWS-TIVIT | H73: Continuacion - Call para gestionar proceso de inicializacion del proyecto AWS Adecuacion de cuentas
B74: 45796 | D74: TIVIT - Operaciones IPS - AWS | E74: Cesar Gonzalez | F74: REQ | G74: IPS FASE 2 - Sesión de levantamiento AWS | H74: Proceso de levantamiento de servicios asociados a las cuentas de AWS IPS
B75: 45797 | D75: TIVIT - Operaciones IPS - AWS | E75: Cesar Gonzalez | F75: REQ | G75: Call IPS Fase II - Daily AWS-TIVIT | H75: Continuacion - Call para gestionar proceso de inicializacion del proyecto AWS Adecuacion de cuentas
B76: 45797 | D76: TIVIT - Operaciones IPS - AWS | E76: Cesar Gonzalez | F76: REQ | G76: Call IPS FASE 2 - Sesión de levantamiento AWS | H76: Continuacion - Call para gestionar proceso de inicializacion del proyecto AWS Adecuacion de cuentas
B77: 45799 | D77: TIVIT - Operaciones IPS - AWS | E77: Cesar Gonzalez | F77: REQ | G77: Call IPS Fase II - Daily AWS-TIVIT | H77: Continuacion - Call para gestionar proceso de inicializacion del proyecto AWS Adecuacion de cuentas
B78: 45799 | D78: Area Ciberseguridad | E78: Cesar Gonzalez | F78: REQ | G78: Ticket N° 14993 - 14982 - Eventos de Seguridad IPS | H78: Ticket para realizar las verificaciones y mitigaciones reportadas por Ciberseguridad.
B79: 45799 | D79: Area Operaciones - TIVIT | E79: Cesar Gonzalez | F79: REQ | G79: Call - Validacion y configuracion Azure DevOps | H79: Call de validacion correspondiente a la creacion de persmisos para usuarios QA dentro de Azure DevOps
... B87: 45804 | D87: Area Ciberseguridad | E87: Cesar Gonzalez | F87: REQ | G87: Ticket N° 15039 - Problemas sitio ciber.ips.gob.cl | H87: Se crea ticket por problemas de conectividad en sitio ciber.ips.gob.cl
E88: Cesar Gonzalez | F88: REQ
B89: 45804 | D89: Area Operaciones - TIVIT | E89: Cesar Gonzalez | F89: REQ | G89: Call - IPS Fase II - Networking AWS | H89: Continuacion - Call para validar configuraciones correspondeintes a Networking y nuevos despliegues de redes.
B90: 45804 | D90: Area Ciberseguridad | E90: Cesar Gonzalez | F90: REQ | G90: IPS FASE 2 - Definición de Servicios de Seguridad a Implementar o Explorar | H90: Call correspondiente a validar y veriticar servicios de seguridad a implmentar.
B91: 45805 | D91: TIVIT - Operaciones IPS - AWS | E91: Cesar Gonzalez | F91: REQ | G91: IPS FASE 2 - SPRINT 1 REVIEW / SPRINT 2 PLANNING | H91: Call de revision de finalizacion de Sprints 1-2
B92: 45806 | D92: TIVIT - Operaciones IPS - AWS | E92: Cesar Gonzalez | F92: REQ | G92: Call IPS Fase II - Daily AWS-TIVIT | H92: Continuacion - Call para gestionar proceso de inicializacion del proyecto AWS Adecuacion de cuentas
B93: 45806 | D93: TIVIT - Operaciones IPS - AWS | E93: Cesar Gonzalez | F93: REQ | G93: IPS FASE 2 - Definir políticas de backup y estrategia de etiquetado | H93: Call correspondiente al proyecto de adecuacion de cuentas en donde se realizaron las validaicones de politicas y etiquetados de ambientes par aservicios de AWS Backup
B94: 45806 | D94: TIVIT - Operaciones IPS - AWS | E94: Cesar Gonzalez | F94: REQ | G94: IPS FASE 2 - DEFINICION DE REPOSITORIOS A UTILIZAR | H94: Call para validar los repositorios que se utilizaran para los despliegues de IaC para lo que es Landing Zone
B95: 45807 | D95: TIVIT - Operaciones IPS - AWS | E95: Cesar Gonzalez | F95: REQ | G95: Call IPS Fase II - Daily AWS-TIVIT | H95: Continuacion - Call para gestionar proceso de inicializacion del proyecto AWS Adecuacion de cuentas
B96: 45810 | C96: JUNIO | D96: TIVIT - Operaciones IPS - AWS | E96: Cesar Gonzalez | F96: REQ | G96: Call IPS Fase II - Daily AWS-TIVIT | H96: Continuacion - Call para gestionar proceso de inicializacion del proyecto AWS Adecuacion de cuentas
B97: 45810 | D97: TIVIT - Operaciones IPS - AWS | E97: Cesar Gonzalez | F97: REQ | G97: Continuacion IPS FASE 2 - DEFINICION DE REPOSITORIOS A UTILIZAR | H97: Call para validar los repositorios que se utilizaran para los despliegues de IaC para lo que es Landing Zone
B98: 45810 | D98: TIVIT - Operaciones IPS - AWS | E98: Cesar Gonzalez | F98: REQ | G98: Call IPS - DEFINICIONES DE ACCESOS A AWS ( IAM IDENTITY CENTER) | H98: Call para definir los accesos, grupos que tendra el despliegue de IAM Identity Center.
B99: 45811 | D99: TIVIT - Operaciones IPS - AWS | E99: Cesar Gonzalez | F99: REQ | G99: Call IPS Fase II - Daily AWS-TIVIT | H99: Continuacion - Call para gestionar proceso de inicializacion del proyecto AWS Adecuacion de cuentas
B100: 45811 | D100: TIVIT - Operaciones IPS - AWS | E100: Cesar Gonzalez | F100: REQ | G100: IPS FASE 2 - Despliegue inicial CT + LZA | H100: Call correspondiente a las configuraciones y despliegues del servicio CT y LZA
B101: 45812 | D101: TIVIT - Operaciones IPS - AWS | E101: Cesar Gonzalez | F101: REQ | G101: Call IPS Fase II - Daily AWS-TIVIT | H101: Continuacion - Call para gestionar proceso de inicializacion del proyecto AWS Adecuacion de cuentas
B102: 45812 | D102: Christian Fuentes IPS | E102: Cesar Gonzalez | F102: REQ | G102: Ticket N° 15120 - Estado Repositorio Documental | 04-06-2025 | H102: Verificar disponiblidad de repositorio S3
B103: 45812 | D103: TIVIT - Operaciones IPS - AWS | E103: Cesar Gonzalez | F103: REQ | G103: IPS FASE 2 - Revisión y priorización de cargas de trabajo a Adecuar | H103: Call para verificar el orden de prioridad que tendra la migracion y adecuacion de cargas para el proyecto de adecuacion de cuentas.
B104: 45813 | D104: TIVIT - Operaciones IPS - AWS | E104: Cesar Gonzalez | F104: REQ | G104: Call IPS Fase II - Daily AWS-TIVIT | H104: Continuacion - Call para gestionar proceso de inicializacion del proyecto AWS Adecuacion de cuentas
B105: 45813 | D105: TIVIT - Operaciones IPS - AWS | E105: Cesar Gonzalez | F105: REQ | G105: Call IPS FASE 2 - Revisión de Normativas de Seguridad 1 | H105: Call para revisar las normativas de seguridad que se aplicaran en nuestros servicios de LZA
B106: 45813 | D106: Luz Maria Rivera | E106: Cesar Gonzalez | F106: REQ | G106: Ticket N° 15144 - Asunto: Solicitud ticket Infraestructura recursos appsservices PROD concesión mayo 2025 | H106: solicitar aumento de recursos del appservice Sdm-back.scm.azurewebsites.net en PROD ya que se requiere realizar el proceso de concesión de mayo 2025. El proceso se ejecutará desde las 18 hrs en adelante para no ejecutar en horario de oficina.
B107: 45814 | D107: TIVIT - Operaciones IPS - AWS | E107: Cesar Gonzalez | F107: REQ | G107: Call IPS Fase II - Daily AWS-TIVIT | H107: Continuacion - Call para gestionar proceso de inicializacion del proyecto AWS Adecuacion de cuentas
B108: 45814 | D108: TIVIT - Operaciones IPS - AWS | E108: Cesar Gonzalez | F108: REQ | G108: Call IPS FASE 2 - Revisión de Frameworks (Cloud Security/Risk) | H108: Call para validar Frameworks correspondientes a servicios Cloud a implementar.
... B135: 45838 | D135: TIVIT - Operaciones IPS - AWS | E135: Cesar Gonzalez | F135: REQ | G135: Call IPS Fase II - Daily AWS-TIVIT | H135: Continuacion - Call para gestionar proceso de inicializacion del proyecto AWS Adecuacion de cuentas
B136: 45839 | C136: JULIO | D136: TIVIT - Operaciones IPS - AWS | E136: Cesar Gonzalez | F136: REQ | G136: Call IPS Fase II - Daily AWS-TIVIT | H136: Continuacion - Call para gestionar proceso de inicializacion del proyecto AWS Adecuacion de cuentas
B137: 45839 | D137: TIVIT - Operaciones IPS | E137: Cesar Gonzalez | F137: REQ | G137: Call MS-TIVIT Ticket: R95489 | H137: Call para realizar las gestiones de tickets y actividades pendientes con TIVIT y MS
B138: 45839 | D138: TIVIT - Operaciones IPS - AWS | E138: Cesar Gonzalez | F138: REQ | G138: Call IPS Fase II - Gitlab Prueba Demo | H138: Call para realizar las validaciones y pruebas demos de ambiente Gitlab
B139: 45840 | D139: TIVIT - Operaciones IPS - AWS | E139: Cesar Gonzalez | F139: REQ | G139: Call IPS Fase II - Daily AWS-TIVIT | H139: Continuacion - Call para gestionar proceso de inicializacion del proyecto AWS Adecuacion de cuentas
B140: 45840 | D140: TIVIT - Operaciones IPS - AWS | E140: Cesar Gonzalez | F140: REQ | G140: Call IPS FASE 2 - Definición de Custom Policies - Identity Center - Levantamiento | H140: En los casos que sea necesario, se agregará una custom policy a los grupos de permisos definidos en el Identity Center para agregar o limitar los accesos otorgados mediante AWS Managed Policies. En esta actividad se propone hacer un levantamiento de las necesidades adicionales a modelar con Custom Policies en cada uno de los grupos de permisos (PermissionSets) desplegados actulmente
B141: 45841 | D141: TIVIT - Operaciones IPS - AWS | E141: Cesar Gonzalez | F141: REQ | G141: Call IPS Fase II - Daily AWS-TIVIT | H141: Continuacion - Call para gestionar proceso de inicializacion del proyecto AWS Adecuacion de cuentas
B142: 45841 | D142: IPS - Jorge Leon Aguilez | E142: Cesar Gonzalez | F142: REQ | G142: Ticket 15388 - Asunto: ODI PRD conexión smtp | H142: Favor generar aranda a INFRA para realizar revisión de conexión entre las máquinas: ODI Prod: 10.150.150.108 Servidor de correo SMTP: email-smtp.us-east-1.amazonaws.com Favor revisar urgente ya que estamos sin poder procesar y notificar del estado de sus archivos a las entidades externas.
B143: 45841 | D143: TIVIT - Operaciones IPS - AWS | E143: Cesar Gonzalez | F143: REQ | G143: Call IPS FASE 2 - DEFINICION ADECUACION A WEB APP VARIAS (MINISITIOS) | H143: Call para realizar las validaciones de los minisitios y servicios que se estaran migrando
B144: 45842 | D144: Operaciones IPS | E144: Cesar Gonzalez | F144: REQ | G144: Call IPS Validacion y Revision ODI | H144: Call para realizar las validaciones y problemas presentados en el envio de correos del ambiente ODI PROD
B145: 45842 | D145: TIVIT - Operaciones IPS - AWS | E145: Cesar Gonzalez | F145: REQ | G145: Call IPS Fase II - Daily AWS-TIVIT | H145: Continuacion - Call para gestionar proceso de inicializacion del proyecto AWS Adecuacion de cuentas
B146: 45842 | D146: TIVIT - Operaciones IPS - Microsoft | E146: Cesar Gonzalez | F146: REQ | G146: Call [EXTERNO]RE: Ticket R95489 | H146: Call para realizar las validaciones con respecto a los servicios Quota/App Services
...

Sheet RodrigoLorca
B1: FECHA SOLICITUD | C1: Periodo | D1: AREA / PERSONAL SOLICITANTE | E1: PROFESIONAL | F1: INC / REQ / WARNING | G1: Actividad | H1: Detalle / Observación | I1: Estado (en proceso, pendiente, finalizado) | J1: Tiempo estimado actividad
B2: 45726 | C2: 45717 | D2: Fernando Lopez - IPS | E2: Rodrigo Lorca | F2: REQ | G2: Transferencia datos criticos entre entidades | H2: Transferencia de archivos criticos archivo fallecidos
B3: 45726 | D3: Ingenieria y Servicios - IPS | E3: Rodrigo Lorca | F3: REQ | G3: Actividades de Administración Plataformas Tecnologicas IPS | H3: Actividades de administración y mantenimiento de los sistemas core de IPS administrados por el área de ingenieria y servicios IPS, destacando coreagil, reforma agil, legados avbmenu, FTPs y SFTPs core IPS, reforma concesión, pisee, SSSonline, asignacion familiar, contacto ips, garantia estatal, reloj virtual, gobierno transparente, mora presunta, entre otros.
B4: 45726 | D4: Jose Luis Hernandez | E4: Rodrigo Lorca | F4: INC | G4: Analisis de Falla masiva en consultas WS Reg Civil | H4: Pruebas y analisis por fallas complejas que afectan a institución en consumo de WS pisee.
B5: 45727 | D5: Jose Luis Hernandez | E5: Rodrigo Lorca | F5: INC | G5: Analisis de Falla masiva en consultas WS Reg Civil | H5: Se hace un analisis detallado del problema presentado en la consulta de WS que consumen la entidad registro civil, se encuentra que el problema era el sobreconsumo por parte de IPS, dado una actividad que estaban realizando desde cliente de negocio desde sucursal santo domingo. Se envia un correo de alerta y aviso por su detención.
B6: 45727 | D6: Carlos Salamanca - IPS | E6: Rodrigo Lorca | F6: REQ | G6: Pasos a producción de sistemas bajo administración | H6: Revisión de documentacion FINS para pasos a producción. R1732 STI - 145466 - 102
B7: 45728 | D7: Sandra Gomez - IPS | E7: Rodrigo Lorca | F7: REQ | G7: Transferencia datos criticos entre entidades | H7: Archivos de consulta BPH para el SRCeI proceso marzo 2025
B8: 45728 | D8: Williams Franco - IPS | E8: Rodrigo Lorca | F8: REQ | G8: Revisión reforma agil | H8: Se realiza revisión y aclaración por problema lenvatado por cliente, generado por utilizar un nodo en especifico y no el DNS balanceado
B9: 45729 | D9: Ingenieria y Servicios - IPS | E9: Rodrigo Lorca | F9: REQ | G9: Actividades de Administración Plataformas Tecnologicas IPS | H9: Actividades de administración y mantenimiento de los sistemas core de IPS administrados por el área de ingenieria y servicios IPS, destacando coreagil, reforma agil, legados avbmenu, FTPs y SFTPs core IPS, reforma concesión, pisee, SSSonline, asignacion familiar, contacto ips, garantia estatal, reloj virtual, gobierno transparente, mora presunta, entre otros.
B10: 45730 | D10: Jose Luis Hernandez | E10: Rodrigo Lorca | F10: INC | G10: Falla Sistema AF | H10: Se realizan acciones de revisión y levantamiento de servicio asignacion familiar que se vio afectado
B11: 45730 | D11: Ingenieria y Servicios - IPS | E11: Rodrigo Lorca | F11: INC | G11: Error avbmenu | H11: Resolución de incidente en AVBmenu
B12: 45730 | D12: Jorge Ahumada - IPS | E12: Rodrigo Lorca | F12: REQ | G12: Modificación servicio programado | H12: Se realiza cambio de configuración horarios de subida y bajada de avbmenu debido a actividad extraordinaria
B13: 45733 | D13: Ingenieria y Servicios - IPS | E13: Rodrigo Lorca | F13: REQ | G13: Actividades de Administración Plataformas Tecnologicas IPS | H13: Actividades de administración y mantenimiento de los sistemas core de IPS administrados por el área de ingenieria y servicios IPS, destacando coreagil, reforma agil, legados avbmenu, FTPs y SFTPs core IPS, reforma concesión, pisee, SSSonline, asignacion familiar, contacto ips, garantia estatal, reloj virtual, gobierno transparente, mora presunta, entre otros.
B14: 45733 | D14: Operaciones - IPS | E14: Rodrigo Lorca | F14: REQ | G14: Gestión de instalación FINS ambientes administrados | H14: Instalación de variadas fichas en ambientes de desarrollo y QA para distintos proyectos que se encuentran llevando a cabo en IPS.
... B52: 45756 | D52: Operaciones - IPS | E52: Rodrigo Lorca | F52: REQ | G52: Gestión de instalación FINS ambientes administrados | H52: Instalación de variadas fichas en ambientes de desarrollo y QA para distintos proyectos que se encuentran llevando a cabo en IPS.
B53: 45757 | C53: 45748 | D53: Ingenieria y Servicios - IPS | E53: Rodrigo Lorca | F53: INC | G53: Falla WebServices Pisee IPS | H53: Analisis y pruebas por falla alertada al momento de consumir los WS desde plataforma Pisee. Se solicita a personal de santo domingo, que puedan proceder a finalizar sus ejecuciones, ya que, se encontraban saturando las consultas y las TPS que la entidad de registro civil tiene permitidas para el instituto.
B54: 45757 | D54: Claudia Flores - IPS | E54: Rodrigo Lorca | F54: INC | G54: Falla y lentitud CoreAgil | H54: Se trabaja en conjunto con soportes de desarrollo, dado los problemas que alertan desde un área de negocio sto domingo, el soporte no encuentra fallas de oepraciones interna y es informado a cliente final.
B55: 45757 | D55: Carlos Salamanca - IPS | E55: Rodrigo Lorca | F55: REQ | G55: Pasos a producción de sistemas bajo administración | H55: Revisión de documentacion FINS para pasos a producción
B56: 45758 | D56: Operaciones - IPS | E56: Rodrigo Lorca | F56: REQ | G56: Gestión de instalación FINS ambientes administrados | H56: Instalación de variadas fichas en ambientes de desarrollo y QA para distintos proyectos que se encuentran llevando a cabo en IPS.
B57: 45761 | D57: Claudia Flores - IPS | E57: Rodrigo Lorca | F57: INC | G57: Falla y lentitud CoreAgil | H57: Se trabaja en conjunto con soportes de desarrollo, dado los problemas que alertan desde un área de negocio sto domingo, el soporte no encuentra fallas de oepraciones interna y es informado a cliente final.
B58: 45761 | D58: Claudia Flores - MAFIPS | E58: Rodrigo Lorca | F58: INC | G58: Error avbmenu | H58: Resolución de incidente en AVBmenu
B59: 45762 | D59: Operaciones - IPS | E59: Rodrigo Lorca | F59: REQ | G59: Gestión de instalación FINS ambientes administrados | H59: Instalación de variadas fichas en ambientes de desarrollo y QA para distintos proyectos que se encuentran llevando a cabo en IPS.
B60: 45763 | D60: Jose Luis Hernandez - IPS | E60: Rodrigo Lorca | F60: REQ | G60: Transferencia datos criticos entre entidades | H60: Transferencia de archivo critico entre IPS y SRCeI
B61: 45763 | D61: Claudia Flores - MAFIPS | E61: Rodrigo Lorca | F61: INC | G61: Error avbmenu | H61: Resolución de incidente en AVBmenu
B62: 45763 | D62: Operaciones - IPS | E62: Rodrigo Lorca | F62: REQ | G62: Gestión de instalación FINS ambientes administrados | H62: Instalación de variadas fichas en ambientes de desarrollo y QA para distintos proyectos que se encuentran llevando a cabo en IPS.
B63: 45764 | D63: Patricio Sotomayor - IPS | E63: Rodrigo Lorca | F63: REQ | G63: Transferencia datos criticos entre entidades | H63: Transferencia de archivo critico entre IPS y SRCeI
B64: 45764 | D64: Ingenieria y Servicios - IPS | E64: Rodrigo Lorca | F64: REQ | G64: Actividades de Administración Plataformas Tecnologicas IPS | H64: Actividades de administración y mantenimiento de los sistemas core de IPS administrados por el área de ingenieria y servicios IPS, destacando coreagil, reforma agil, legados avbmenu, FTPs y SFTPs core IPS, reforma concesión, pisee, SSSonline, asignacion familiar, contacto ips, garantia estatal, reloj virtual, gobierno transparente, mora presunta, entre otros.
B65: 45768 | D65: Fernando Lopez - IPS | E65: Rodrigo Lorca | F65: REQ | G65: Transferencia datos criticos entre entidades | H65: Transferencia de archivos criticos archivo fallecidos
... B98: 45786 | D98: Alejandra Luna - IPS | E98: Rodrigo Lorca | F98: REQ | G98: Reinicio nodo core agil | H98: Se realiza reinicio de servicio nodo core agil
B99: 45787 | C99: 45778 | D99: NOC - Abenis & Patricio Soyomayor - IPS | E99: Rodrigo Lorca | F99: INC | G99: Incidente AF | H99: Se realiza levantamiento de servicio productivo caido asociado a asignación familiar
B100: 45787 | D100: IPS | E100: Rodrigo Lorca | F100: REQ | G100: Proceso CDP Mensual | H100: Se modifican parametros y validación de servicios legados avbmenu por excepción de proceso horario Autraliano.
B101: 45788 | D101: IPS | E101: Rodrigo Lorca | F101: REQ | G101: Proceso CDP Mensual | H101: Se modifican parametros y validación de servicios legados avbmenu por excepción de proceso horario Autraliano.
B102: 45789 | D102: Victor Muñoz - IPS | E102: Rodrigo Lorca | F102: REQ | G102: Transferencia datos criticos entre entidades | H102: Transferencia de archivos criticos archivo fallecidos
B103: 45789 | D103: Ingenieria y Servicios - IPS | E103: Rodrigo Lorca | F103: REQ | G103: Actividades de Administración Plataformas Tecnologicas IPS | H103: Actividades de administración y mantenimiento de los sistemas core de IPS administrados por el área de ingenieria y servicios IPS, destacando coreagil, reforma agil, legados avbmenu, FTPs y SFTPs core IPS, reforma concesión, pisee, SSSonline, asignacion familiar, contacto ips, garantia estatal, reloj virtual, gobierno transparente, mora presunta, entre otros.
B104: 45789 | D104: Ingenieria y Servicios - IPS | E104: Rodrigo Lorca | F104: INC | G104: Errores Inesperados Core Agil | H104: Se realiza analisis y posterior solución a problemas de errores inesperados presentados en core agil
B105: 45790 | D105: Operaciones - IPS | E105: Rodrigo Lorca | F105: REQ | G105: Gestión de instalación FINS ambientes administrados | H105: Instalación de variadas fichas en ambientes de desarrollo y QA para distintos proyectos que se encuentran llevando a cabo en IPS.
B106: 45791 | D106: Ingenieria y Servicios - IPS | E106: Rodrigo Lorca | F106: REQ | G106: Actividades de Administración Plataformas Tecnologicas IPS | H106: Actividades de administración y mantenimiento de los sistemas core de IPS administrados por el área de ingenieria y servicios IPS, destacando coreagil, reforma agil, legados avbmenu, FTPs y SFTPs core IPS, reforma concesión, pisee, SSSonline, asignacion familiar, contacto ips, garantia estatal, reloj virtual, gobierno transparente, mora presunta, entre otros.
B107: 45792 | D107: Williams Franco - MAFIPS | E107: Rodrigo Lorca | F107: INC | G107: Error avbmenu | H107: Se valida problema de lentitud en servicio avbmenu, sin encontrar problema reportado u otro. Se le pide a mafips que analicen directamente la sucursal o equipos de usuarios finales.
B108: 45793 | D108: Ingenieria y Servicios - IPS | E108: Rodrigo Lorca | F108: REQ | G108: Reforma QA y problemas de lentitud | H108: Se realizan variadas pruebas con personal de soporte de desarrollo, y se encuentra en horario AM que habian realizado una copia mal desde producción a la DB de QA. Luego de esto, sigue el problema de lentitud, y se pide la deshabilitación de politicas desde servidor de aplicación QA para descartar problemas de FW.
B109: 45793 | D109: Operaciones - IPS | E109: Rodrigo Lorca | F109: REQ | G109: Gestión de instalación FINS ambientes administrados | H109: Instalación de variadas fichas en ambientes de desarrollo y QA para distintos proyectos que se encuentran llevando a cabo en IPS.
B110: 45796 | D110: NOC - Abenis | E110: Rodrigo Lorca | F110: INC | G110: Incidente AF | H110: Se realiza levantamiento de servicio productivo caido asociado a asignación familiar
B111: 45796 | D111: Ingenieria y Servicios - IPS | E111: Rodrigo Lorca | F111: REQ | G111: Reunión Reforma QA y problemas | H111: Se realiza analisis en conjunto con variadas áreas, para solucionar problema de consultas en Reforma QA. En donde, se encuentra que el problema radicaba en que era un permiso hacia Pisee Prod puerto 80.
... B119: 45797 | D119: Jandi Vasquez - IPS | E119: Rodrigo Lorca | F119: INC | G119: Servicio Proceso BONO | H119: Se realiza levantamiento de proceso Bono solicitado por personal de soporte core agil
F120: -
B121: 45798 | D121: Cristian Abarca - IPS | E121: Rodrigo Lorca | F121: INC | G121: Incidente servidor Batch Core | H121: Se debe trabajar en validación de server y posterior levantamiento de servicios por caida de Servidor Batch Core, por kernel panic generado en proveedor de servicio
B122: 45799 | D122: Carlos Salamanca - UPS | E122: Rodrigo Lorca | F122: REQ | G122: Paso a producción | H122: Paso a producción R1759 STI - 150146 - 134
B123: 45799 | D123: Manuel Huenchullan - IPS | E123: Rodrigo Lorca | F123: REQ | G123: Transferencia datos criticos entre entidades | H123: Validación de actividad automatica de envio archivos criticos a SP
B124: 45800 | D124: Manuel Soto - Auditoria IPS | E124: Rodrigo Lorca | F124: REQ | G124: Tabla SRCeI | H124: Apoyo en obtención de documentación mensual sobre Tabla SRCeI
B125: 45800 | D125: Paola Arriaza - IPS | E125: Rodrigo Lorca | F125: REQ | G125: Transferencia datos criticos entre entidades | H125: Transferencia de archivos criticos Acreditación de Matrimonio
B126: 45803 | D126: Operaciones - IPS | E126: Rodrigo Lorca | F126: REQ | G126: Gestión de instalación FINS ambientes administrados | H126: Instalación de variadas fichas en ambientes de desarrollo y QA para distintos proyectos que se encuentran llevando a cabo en IPS.
B127: 45803 | D127: Victor Muñoz - IPS | E127: Rodrigo Lorca | F127: REQ | G127: Transferencia datos criticos entre entidades | H127: Transferencia de archivos criticos archivo fallecidos
B128: 45803 | D128: Jose Luis Hernandez - IPS | E128: Rodrigo Lorca | F128: REQ | G128: Validación servicio AF Productivo | H128: Se realiza validación AM por cambio de servidor DB productiva GenesysP durante el fin de semana, el cual, afecto directamente al aplicativo y tuvo que ser reiniciado.
B129: 45804 | D129: Ingenieria y Servicios - IPS | E129: Rodrigo Lorca | F129: REQ | G129: Actividades de Administración Plataformas Tecnologicas IPS | H129: Actividades de administración y mantenimiento de los sistemas core de IPS administrados por el área de ingenieria y servicios IPS, destacando coreagil, reforma agil, legados avbmenu, FTPs y SFTPs core IPS, reforma concesión, pisee, SSSonline, asignacion familiar, contacto ips, garantia estatal, reloj virtual, gobierno transparente, mora presunta, entre otros.
B130: 45805 | D130: Operaciones - IPS | E130: Rodrigo Lorca | F130: REQ | G130: Gestión de instalación FINS ambientes administrados | H130: Instalación de variadas fichas en ambientes de desarrollo y QA para distintos proyectos que se encuentran llevando a cabo en IPS.
B131: 45806 | D131: Carlos Salamanca - IPS | E131: Rodrigo Lorca | F131: REQ | G131: Paso a producción | H131: Paso a Producción Arandas 150832-151032-151080-147508 - Atención y Concesión
B132: 45806 | D132: Carlos Salamanca - IPS | E132: Rodrigo Lorca | F132: REQ | G132: Paso a producción | H132: Paso a producción AR 151143 Reforma Agil
... B147: 45817 | D147: Omar Salas - IPS | E147: Rodrigo Lorca | F147: REQ | G147: Transferencia datos criticos entre entidades | H147: Transferencia de archivos criticos archivo fallecidos
B148: 45818 | C148: 45809 | D148: Ingenieria y Servicios - IPS | E148: Rodrigo Lorca | F148: INC | G148: Revisión Pisee | H148: Se analizan WS del registro Civil por problemas de intermintencia en consultas a WS entidad externa especifica. Se levanta caso a segpres y se recibe información de fallas en la entidad externa.
B149: 45818 | D149: Ingenieria y Servicios - IPS | E149: Rodrigo Lorca | F149: INC | G149: AVBmenu Fallas | H149: Problemas en avbmenu por caida de DB informix.
B150: 45819 | D150: Ingenieria y Servicios - IPS | E150: Rodrigo Lorca | F150: REQ | G150: Actividades de Administración Plataformas Tecnologicas IPS | H150: Actividades de administración y mantenimiento de los sistemas core de IPS administrados por el área de ingenieria y servicios IPS, destacando coreagil, reforma agil, legados avbmenu, FTPs y SFTPs core IPS, reforma concesión, pisee, SSSonline, asignacion familiar, contacto ips, garantia estatal, reloj virtual, gobierno transparente, mora presunta, entre otros.
B151: 45819 | D151: Operaciones - IPS | E151: Rodrigo Lorca | F151: REQ | G151: Gestión de instalación FINS ambientes administrados | H151: Instalación de variadas fichas en ambientes de desarrollo y QA para distintos proyectos que se encuentran llevando a cabo en IPS.
B152: 45820 | D152: Ingenieria y Servicios - IPS | E152: Rodrigo Lorca | F152: INC | G152: Revisión Pisee | H152: Cambio de certificado SSL de pisee.cl el cual no fue avisado previamente por entidad correspondiente
B153: 45820 | D153: Operaciones - IPS | E153: Rodrigo Lorca | F153: REQ | G153: Gestión de instalación FINS ambientes administrados | H153: Instalación de variadas fichas en ambientes de desarrollo y QA para distintos proyectos que se encuentran llevando a cabo en IPS.
B154: 45821 | D154: Operaciones - IPS | E154: Rodrigo Lorca | F154: REQ | G154: Gestión de instalación FINS ambientes administrados | H154: Instalación de variadas fichas en ambientes de desarrollo y QA para distintos proyectos que se encuentran llevando a cabo en IPS.
B155: 45824 | D155: Fernando Lopez - IPS | E155: Rodrigo Lorca | F155: REQ | G155: Transferencia datos criticos entre entidades | H155: Transferencia de archivos criticos archivo fallecidos
B156: 45824 | D156: Operaciones - IPS | E156: Rodrigo Lorca | F156: REQ | G156: Gestión de instalación FINS ambientes administrados | H156: Instalación de variadas fichas en ambientes de desarrollo y QA para distintos proyectos que se encuentran llevando a cabo en IPS.
B157: 45825 | D157: Jose Miguel Ruiz - MAFIPS | E157: Rodrigo Lorca | F157: INC | G157: Alerta por problemas Coreagil y Avbmenu | H157: Se realiza analisis de servidores Core IPS por alertas generadas por usuarios, siendo ambas alertas descartadas, dado que no se encontraron fallas por nuestra parte.
B158: 45826 | D158: Ingenieria y Servicios - IPS | E158: Rodrigo Lorca | F158: INC | G158: Error avbmenu | H158: Resolución de incidente en AVBmenu
B159: 45826 | D159: Carlos Salamanca - IPS | E159: Rodrigo Lorca | F159: REQ | G159: Paso a producción | H159: ECER: R1769 Aranda(s) 152565 - STI
B160: 45826 | D160: Carlos Salamanca - IPS | E160: Rodrigo Lorca | F160: REQ | G160: Paso a producción | H160: paso a Producción Aranda 149808 "Agregar Deuda nominal trabajador en anexo 2 de titulo ejecutivo". Paso con error y se realiza rollback
... B187: 45847 | D187: Paola Lillo - IPS | E187: Rodrigo Lorca | F187: REQ | G187: Revisión de espacios FS Servidores Productivos | H187: Se realiza gestión de espacio en servidor productivo insitucional de sistema Asignación Familiar
B188: 45848 | C188: 45839 | D188: Manuel Huenchullan - IPS | E188: Rodrigo Lorca | F188: REQ | G188: Transferencia datos criticos entre entidades | H188: Validación de actividad automatica de envio archivos criticos a SP
B189: 45848 | D189: Jose Luis Hernandez - IPS | E189: Rodrigo Lorca | F189: REQ | G189: Certificado Firma Digital Pisee | H189: Se trabaja en conjunto con personal IPS para la compra y obtención del certificado de firma digital para plataforma Pisee, la cual, tiene fecha de caducidad el día 12 de Julio del 2025.
B190: 45848 | D190: Ingenieria y Servicios - IPS | E190: Rodrigo Lorca | F190: INC | G190: AVBmenu Fallas | H190: Problemas en avbmenu por problema de DB informix. Realizan reinicio de motor de DB.
B191: 45848 | D191: Operaciones - IPS | E191: Rodrigo Lorca | F191: REQ | G191: Gestión de instalación FINS ambientes administrados | H191: Instalación de variadas fichas en ambientes de desarrollo y QA para distintos proyectos que se encuentran llevando a cabo en IPS.
B192: 45849 | D192: Jose Luis Hernandez - IPS | E192: Rodrigo Lorca | F192: REQ | G192: Proceso CDP Mensual | H192: Se modifican parametros y validación de servicios legados avbmenu por excepción de proceso horario Autraliano.
B193: 45849 | D193: Jose Luis Hernandez - IPS | E193: Rodrigo Lorca | F193: REQ | G193: Certificado Firma Digital Pisee | H193: Se gestiona la instalación de certificado de firma digital con entidad de registro civil.
B194: 45849 | D194: Operaciones - IPS | E194: Rodrigo Lorca | F194: INC | G194: AVBmenu Fallas | H194: Trabajos de apoyo por problemas generados por carga de servidor base de datos Informix.
B195: 45849 | D195: Jose Luis Hernandez - IPS | E195: Rodrigo Lorca | F195: REQ | G195: Certificado Firma Digital Pisee | H195: Se gestiona la instalación de certificado de firma digital con entidad de registro civil.
B196: 45852 | D196: Omar Salas - IPS | E196: Rodrigo Lorca | F196: REQ | G196: Transferencia datos criticos entre entidades | H196: Transferencia de archivos criticos archivo fallecidos
B197: 45852 | D197: Claudia Flores - IPS | E197: Rodrigo Lorca | F197: INC | G197: Incidencia WS Registro Civil | H197: Se realiza analisis por intermitencia de consulta a WS de entidad Registro Civil, las cuales, se generan a causa de proceso ejecutado desde sucursal santo domingo en horario indebido.
B198: 45853 | D198: Operaciones - IPS | E198: Rodrigo Lorca | F198: REQ | G198: Gestión de instalación FINS ambientes administrados | H198: Instalación de variadas fichas en ambientes de desarrollo y QA para distintos proyectos que se encuentran llevando a cabo en IPS.
B199: 45854 | D199: Ingenieria y Servicios - IPS | E199: Rodrigo Lorca | F199: REQ | G199: Actividades de Administración Plataformas Tecnologicas IPS | H199: Actividades de administración y mantenimiento de los sistemas core de IPS administrados por el área de ingenieria y servicios IPS, destacando coreagil, reforma agil, legados avbmenu, FTPs y SFTPs core IPS, reforma concesión, pisee, SSSonline, asignacion familiar, contacto ips, garantia estatal, reloj virtual, gobierno transparente, mora presunta, entre otros.
B200: 45855 | D200: Claudia Flores | E200: Rodrigo Lorca | F200: INC | G200: Revisión alerta siio ley19992fase2 | H200: Se revisa sitio http://ley19992fase2.intranet.ips.gob.cl/loginad/ sin encontrar problema
... B231: 45877 | D231: Operaciones - IPS | E231: Rodrigo Lorca | F231: REQ | G231: Gestión de instalación FINS ambientes administrados | H231: Instalación de variadas fichas en ambientes de desarrollo y QA para distintos proyectos que se encuentran llevando a cabo en IPS.
F232: -
B233: 45880 | C233: 45870 | D233: Omar Salas - IPS | E233: Rodrigo Lorca | F233: REQ | G233: Transferencia datos criticos entre entidades | H233: Transferencia de archivos criticos archivo fallecidos
B234: 45880 | C234: 45870 | D234: Operaciones - IPS | E234: Rodrigo Lorca | F234: REQ | G234: Gestión de instalación FINS ambientes administrados | H234: Instalación de variadas fichas en ambientes de desarrollo y QA para distintos proyectos que se encuentran llevando a cabo en IPS.
B235: 45881 | C235: 45870 | D235: Ingenieria y Servicios - IPS | E235: Rodrigo Lorca | F235: REQ | G235: Actividades de Administración Plataformas Tecnologicas IPS | H235: Actividades de administración y mantenimiento de los sistemas core de IPS administrados por el área de ingenieria y servicios IPS, destacando coreagil, reforma agil, legados avbmenu, FTPs y SFTPs core IPS, reforma concesión, pisee, SSSonline, asignacion familiar, contacto ips, garantia estatal, reloj virtual, gobierno transparente, mora presunta, entre otros.
B236: 45881 | C236: 45870 | D236: Manuel Huenchullan - IPS | E236: Rodrigo Lorca | F236: REQ | G236: Transferencia datos criticos entre entidades | H236: Validación de actividad automatica de envio archivos criticos a SP
B237: 45881 | C237: 45870 | D237: Jose Miguel Ruiz - MAFIPS | E237: Rodrigo Lorca | F237: INC | G237: Lentitud Core Agil | H237: Se validan servicios productivos por problemas generados a causa de sobre carga DB Core IPS
B238: 45881 | C238: 45870 | D238: Carlos Salamanca - IPS | E238: Rodrigo Lorca | F238: REQ | G238: Paso a producción | H238: R1788 sti - 153234 - 168
B239: 45882 | C239: 45870 | D239: Operaciones - IPS | E239: Rodrigo Lorca | F239: REQ | G239: Gestión de instalación FINS ambientes administrados | H239: Instalación de variadas fichas en ambientes de desarrollo y QA para distintos proyectos que se encuentran llevando a cabo en IPS.
B240: 45883 | C240: 45870 | D240: Ingenieria y Servicios - IPS | E240: Rodrigo Lorca | F240: REQ | G240: Actividades de Administración Plataformas Tecnologicas IPS | H240: Actividades de administración y mantenimiento de los sistemas core de IPS administrados por el área de ingenieria y servicios IPS, destacando coreagil, reforma agil, legados avbmenu, FTPs y SFTPs core IPS, reforma concesión, pisee, SSSonline, asignacion familiar, contacto ips, garantia estatal, reloj virtual, gobierno transparente, mora presunta, entre otros.
B241: 45884 | C241: 45870 | D241: Operaciones - IPS | E241: Rodrigo Lorca | F241: REQ | G241: Gestión de instalación FINS ambientes administrados | H241: Instalación de variadas fichas en ambientes de desarrollo y QA para distintos proyectos que se encuentran llevando a cabo en IPS.
B242: 45887 | C242: 45870 | D242: Ingenieria y Servicios - IPS | E242: Rodrigo Lorca | F242: REQ | G242: Actividades de Administración Plataformas Tecnologicas IPS | H242: Actividades de administración y mantenimiento de los sistemas core de IPS administrados por el área de ingenieria y servicios IPS, destacando coreagil, reforma agil, legados avbmenu, FTPs y SFTPs core IPS, reforma concesión, pisee, SSSonline, asignacion familiar, contacto ips, garantia estatal, reloj virtual, gobierno transparente, mora presunta, entre otros.
B243: 45887 | C243: 45870 | D243: Victor Muñoz - IPS | E243: Rodrigo Lorca | F243: REQ | G243: Transferencia datos criticos entre entidades | H243: Validación de actividad automatica de envio archivos criticos a SP
B244: 45888 | C244: 45870 | D244: Ingenieria y Servicios - IPS | E244: Rodrigo Lorca | F244: INC | G244: Error avbmenu | H244: Resolución de incidente en AVBmenu
... B271: 45909 | C271: 45870 | D271: Operaciones - IPS | E271: Rodrigo Lorca | F271: REQ | G271: Gestión de instalación FINS ambientes administrados | H271: Instalación de variadas fichas en ambientes de desarrollo y QA para distintos proyectos que se encuentran llevando a cabo en IPS.
F272: -
...

Sheet PabloSalazar
B1: FECHA SOLICITUD | C1: Periodo | D1: AREA / PERSONAL SOLICITANTE | E1: PROFESIONAL | F1: INC / REQ / WARNING | G1: Actividad | H1: Detalle / Observación | I1: Estado (en proceso, pendiente, finalizado) | J1: Tiempo estimado actividad
B2: 45748 | C2: 45748 | D2: Gonzalo Sepulveda | E2: Pablo Salazar | F2: REQ | G2: 10.150.234.185 ayuda con accesos
B3: 45749 | C3: 45749 | D3: Gonzalo Sepulveda | E3: Pablo Salazar | F3: REQ | G3: 10.150.234.185 ayuda con accesos
B4: 45750 | C4: 45750 | D4: Area de segurida informatica | E4: Pablo Salazar | F4: REQ | G4: hallazgo Primeface y java
B5: 45751 | C5: 45751 | D5: Area de segurida informatica | E5: Pablo Salazar | F5: INC | G5: hallazgo Primeface y java
B6: 45754 | C6: 45752 | D6: Area de segurida informatica | E6: Pablo Salazar | F6: REQ | G6: hallazgo Primeface y java
B7: 45755 | C7: 45753 | D7: Oscar Luis Mora Araya | E7: Pablo Salazar | F7: REQ | G7: OHSProd01.ips.gob.cl revision
B8: 45756 | C8: 45754 | D8: Iann Isaias Sandoval Gonzalez | E8: Pablo Salazar | F8: REQ | G8: Aranda 14562, accesos a servidores
B9: 45757 | C9: 45755 | D9: Iann Isaias Sandoval Gonzalez | E9: Pablo Salazar | F9: REQ | G9: Aranda 14562, accesos a servidores
B10: 45758 | C10: 45756 | D10: Francis Ostos | E10: Pablo Salazar | F10: REQ | G10: acceosos a RelojVirtual y srv-relojcontrol
B11: 45761 | C11: 45757 | D11: Francis Ostos | E11: Pablo Salazar | F11: REQ | G11: acceosos a RelojVirtual y srv-relojcontrol
B12: 45762 | C12: 45758 | D12: Paola Lillo | E12: Pablo Salazar | F12: REQ | G12: cuenta de alejandro Ipinza en los linux
B13: 45763 | C13: 45759 | D13: Paola Lillo | E13: Pablo Salazar | F13: REQ | G13: cuenta de alejandro Ipinza en los linux
... B226: 46066 | C226: 46064 | D226: mesa de ayuda | E226: Pablo Salazar | F226: REQ | G226: espacio en server pirihuico
B227: 46069 | C227: 46065 | E227: Pablo Salazar | G227: vacaciones
B228: 46070 | C228: 46066 | E228: Pablo Salazar | G228: vacaciones
B229: 46071 | C229: 46067 | E229: Pablo Salazar | G229: vacaciones
B230: 46072 | C230: 46068 | E230: Pablo Salazar | G230: vacaciones
B231: 46073 | C231: 46069 | E231: Pablo Salazar | G231: vacaciones
B232: 46076 | C232: 46070 | E232: Pablo Salazar | G232: vacaciones
B233: 46077 | C233: 46071 | E233: Pablo Salazar | G233: vacaciones
B234: 46078 | C234: 46072 | E234: Pablo Salazar | G234: vacaciones
B235: 46079 | C235: 46073 | E235: Pablo Salazar | G235: vacaciones
B236: 46080 | C236: 46074 | E236: Pablo Salazar | G236: vacaciones
B237: 46083 | C237: 46083 | D237: mesa de ayuda | E237: Pablo Salazar | F237: REQ | G237: -ALERTAS DE DISCO servidor AWS -Asistencia alerta espacio en disco servidor AWS - Wlsprod03 IP 10.200.2.253
B238: 46084 | C238: 46084 | D238: mesa de ayuda | E238: Pablo Salazar | F238: REQ | G238: -alertas AZS4HANAPRD01 IP 10.88.1.135
B239: 46085 | C239: 46085 | D239: mesa de ayuda | E239: Pablo Salazar | F239: REQ | G239: -alertas AZS4HANAPRD01 IP 10.88.1.136
B240: 46086 | C240: 46086 | D240: mesa de ayuda /infraestructura | E240: Pablo Salazar | F240: REQ | G240: -aranda 17330 -agente en unas maquinas de AWS
B241: 46087 | C241: 46087 | D241: infraestructura | E241: Pablo Salazar | F241: REQ | G241: trabajos aws key fjilbertof
B242: 46090 | C242: 46088 | D242: infraestructura | E242: Pablo Salazar | F242: REQ | G242: capacidad de discos server aws ipv6 en el SOLMAN
B243: 46091 | C243: 46089 | D243: infraestructura | E243: Pablo Salazar | F243: REQ | G243: capacidad de discos server aws ipv6 en el SOLMAN
B244: 46092 | C244: 46090 | D244: infraestructura | E244: Pablo Salazar | F244: REQ | G244: capacidad de discos server aws | H244: Se trabaja en planilla envida por Daniel Zamora para saber la capacidad de disco de una granja en una granja de server | I244: 3h | J244: finalizado
B245: 46093 | C245: 46091 | D245: infraestructura | E245: Pablo Salazar | F245: REQ | G245: capacidad de discos server aws | H245: Se trabaja en planilla envida por Daniel Zamora para saber la capacidad de disco de una granja en una granja de server | I245: 2h | J245: finalizado
B246: 46094 | C246: 46092 | D246: infraestructura | E246: Pablo Salazar | F246: REQ | G246: capacidad de discos server aws | H246: Se trabaja en planilla envida por Daniel Zamora para saber la capacidad de disco de una granja en una granja de server | I246: 3h | J246: finalizado
B247: 46097 | C247: 46093 | D247: infraestructura | E247: Pablo Salazar | F247: REQ | G247: key maquinas aws | H247: Se trabaja en maquinas de aws en el orden de sus .pem y .pub. Anotando en planillas para su facilidad al acceder. | I247: 2h | J247: finalizado
B248: 46098 | C248: 46094 | D248: infraestructura | E248: Pablo Salazar | F248: REQ | G248: key maquinas aws / trabajos en planilla de maquinas virtules | H248: Se trabaja en maquinas de aws en el orden de sus .pem y .pub. Anotando en planillas para su facilidad al acceder. / Se mantiene el orden de infraestructura de cada maquina administrada, cpu,discos, ram,etc. | I248: 3h | J248: finalizado
B249: 46099 | C249: 46095 | D249: infraestructura | E249: Pablo Salazar | F249: REQ | G249: key maquinas aws / trabajos en planilla de maquinas virtules | H249: Se trabaja en maquinas de aws en el orden de sus .pem y .pub. Anotando en planillas para su facilidad al acceder. / Se mantiene el orden de infraestructura de cada maquina administrada, cpu,discos, ram,etc. | I249: 3h | J249: finalizado
B250: 46100 | C250: 46096 | D250: infraestructura | E250: Pablo Salazar | F250: REQ | G250: trabajos en planilla de maquinas virtules | H250: Se mantiene el orden de infraestructura de cada maquina administrada, cpu,discos, ram,etc. | I250: 2h | J250: finalizado
B251: 46101 | C251: 46097 | D251: infraestructura | E251: Pablo Salazar | F251: REQ | G251: trabajos en planilla de maquinas virtules | H251: Se mantiene el orden de infraestructura de cada maquina administrada, cpu,discos, ram,etc. | I251: 2h | J251: finalizado
B252: 46104 | C252: 46098 | D252: infraestructura | E252: Pablo Salazar | F252: REQ | G252: revision aranda ticket | H252: se revisa aranda para saver si ahi requeriineto nuevos, y lo antiguos para poder avanzar en ellos. | I252: 30 min | J252: finalizado
B253: 46104 | C253: 46099 | D253: infraestructura | E253: Pablo Salazar | F253: REQ | G253: revision aranda ticket | H253: se revisa aranda para saver si ahi requeriineto nuevos, y lo antiguos para poder avanzar en ellos. | I253: 30 min | J253: finalizado
B254: 46105 | C254: 46100 | D254: infraestructura | E254: Pablo Salazar | F254: REQ | G254: revision aranda ticket | H254: se ingresa server por seever para saver si tenemos adinistracion para un pocible upgrde de SO. | I254: 30min | J254: finalizado
B255: 46106 | C255: 46101 | D255: Jose Cruces | E255: Pablo Salazar | F255: REQ | G255: revicion de accesos a server para upgrade en SO/ apoyo equipo Mitheware puertos server. | H255: se ingresa server por seever para saver si tenemos adinistracion para un pocible upgrde de SO. | I255: 6h | J255: en proceso
... B257: 46108 | C257: 46103 | D257: infraestructura | E257: Pablo Salazar | F257: REQ | G257: Reunion de presentacion de equipo infraestructura | H257: reunión de de presentacion de equipo, proyectos y estrategias de infraestructura. | I257: 2h | J257: finalizado

Sheet GonzaloRodriguez
B1: FECHA SOLICITUD | C1: Periodo | D1: AREA / PERSONAL SOLICITANTE | E1: PROFESIONAL | F1: INC / REQ / WARNING | G1: Actividad | H1: Detalle / Observación | I1: Estado (en proceso, pendiente, finalizado) | J1: Tiempo estimado actividad
B2: 45726 | C2: 45717 | D2: Paola Lillo | E2: Gonzalo Rodriguez | F2: REQ | G2: Migración a Discos Administrados MV Azure | H2: Realizar migracion de discos administrado en MV apagadas (Robot)
B3: 45737 | C3: 45717 | D3: Paola Lillo | E3: Gonzalo Rodriguez | F3: REQ | G3: Migración a Discos Administrados MV Azure | H3: Realizar migracion de discos administrado en MV apagadas (Robot)
B4: 45740 | C4: 45717 | D4: Paola Lillo | E4: Gonzalo Rodriguez | F4: REQ | G4: Documentación de vpn Azure y AWS | H4: Generar documentación entre las vpn de Azure y AWS
B5: 45741 | C5: 45717 | D5: Paola Lillo | E5: Gonzalo Rodriguez | F5: REQ | G5: Documentación de Firewall Palo Alto | H5: Generar documentación de FW Palo Alto Azure
B6: 45741 | C6: 45717 | D6: Pamela Nogues | E6: Gonzalo Rodriguez | F6: REQ | G6: Redireccion de tráfico hacia internet por Firewall Palo Alto Azure | H6: Configuración de FW y creación de las tablas de rutas para subredes de Desarrollo
B7: 45741 | C7: 45717 | D7: Ricardo Briones | E7: Gonzalo Rodriguez | F7: REQ | G7: Ticket 14376 - Permisos App Service | H7: Se otorgan permisos Website Contributor a usuario Christian Fuentes para apps Hpfront-prd y Hpback-prd
B8: 45742 | C8: 45717 | D8: Gonzalo Sepulveda | E8: Gonzalo Rodriguez | F8: REQ | G8: Ticket 14386 - Apagado Maquinas Virtuales AWS | H8: Se deshabilita apaga automatico instancias PDP UAT
B9: 45743 | C9: 45717 | D9: Gonzalo Sepulveda | E9: Gonzalo Rodriguez | F9: REQ | G9: Ticket 14399 - Apagado Maquinas Virtuales AWS | H9: Se deshabilita apaga automatico instancias PDP UAT
B10: 45744 | C10: 45717 | D10: Pamela Nogues | E10: Gonzalo Rodriguez | F10: REQ | G10: Levantamiento MV produccion Azure | H10: Se entrega detalle de todas las MV de producción
B11: 45748 | C11: 45748 | D11: Gonzalo Sepulveda | E11: Gonzalo Rodriguez | F11: REQ | G11: Ticket 14456 - Apagado Maquinas Virtuales AWS | H11: Se deshabilita apaga automatico instancias PDP UAT
B12: 45749 | C12: 45748 | D12: Pamela Nogues | E12: Gonzalo Rodriguez | F12: REQ | G12: Levantamiento Subnets produccion Azure | H12: Se entrega detalle de todas las Subnets de producción
B13: 45750 | C13: 45748 | D13: Daniel Zamora + TIVIT | E13: Gonzalo Rodriguez | F13: REQ | G13: Azure Devops | H13: Se crea nueva suscripcion en cuenta IPS-CHILE-AE e implementación de herramienta Azure Devops
... B17: 45762 | C17: 45748 | D17: Daniel Zamora | E17: Gonzalo Rodriguez | F17: REQ | G17: Azure Devops | H17: Reunion con Chile Atiende sobre experiencia e Implementacion de Azure Devops
B18: 17/04/2025 | C18: 46113 | D18: Gonzalo Sepúlveda | E18: Gonzalo Rodriguez | F18: REQ | G18: Deshablitar autoapagado | H18: no realizar el apagado de las máquinas de PDP del ambiente SIT
B19: 21/04/2025 | C19: 46478 | D19: Gonzalo Sepúlveda | E19: Gonzalo Rodriguez | F19: REQ | G19: Deshablitar autoapagado | H19: no realizar el apagado del ambiente de DEV de PDP
B20: 22/04/2025 | C20: 46844 | D20: Carlos Leins | E20: Gonzalo Rodriguez | F20: REQ | G20: Firewall PAN | H20: Preparacion para integracion de firewall PAN en ambiente productivo
B21: 23/04/2025 | C21: 47209 | D21: Gonzalo Sepúlveda | E21: Gonzalo Rodriguez | F21: REQ | G21: Deshablitar autoapagado | H21: deshabilitación del apagado de la máquina de SIT del ambiente de PDP
B22: 24/04/2025 | C22: 47574 | D22: Jorge Echenique | E22: Gonzalo Rodriguez | F22: REQ | G22: Revsion app service | H22: revisión de appservices tramites digitales ambiente QA para validar funcionamiento de servicios instalados.
B23: 45772 | C23: 47939 | D23: Sergio Santibañez | E23: Gonzalo Rodriguez | F23: REQ | G23: Encendido de MV | H23: Se solicita subir maquinas UAT de AFPER uat-afper-consulta.ips.gob.cl, uat-afper-consulta-2.ips.gob.cl, uat-afper-reclamo.ips.gob.cl
B24: 45775 | C24: 48305 | D24: Patricio Pizarro | E24: Gonzalo Rodriguez | F24: INC | G24: Alerta por intentos de inyección SQL a través de tráfico HTTP | H24: Los intentos provinieron de las IPs 10.88.7.4 y 10.88.7.8, utilizando distintos puertos de origen hacia IP 10.151.2.35
B25: 45779 | C25: 48670 | D25: Gabriel Nunez | E25: Gonzalo Rodriguez | F25: REQ | G25: Encendido de MV | H25: mantener encendidos ambientes sit y dev del portal de pago
B26: 45782 | C26: 45778 | D26: Pamela Nogues | E26: Gonzalo Rodriguez | F26: REQ | G26: Configuración Palo Alto Firewall PAN HA | H26: Definiciones
B27: 45790 | C27: 45778 | D27: Team AWS | E27: Gonzalo Rodriguez | F27: REQ | G27: AWS Landing Zone Fase 2 | H27: Inicio Fase II, parte 1
B28: 45790 | C28: 45778 | D28: Team AWS | E28: Gonzalo Rodriguez | F28: REQ | G28: AWS Landing Zone Fase 2 | H28: Inicio Fase II, parte 2
B29: 45791 | C29: 45778 | D29: Gonzalo Sepulveda | E29: Gonzalo Rodriguez | F29: REQ | G29: Apagado Automático EC2 | H29: Deshabilitar Apagado automático Ambiente SIT Portal de Pago
B30: 45793 | C30: 45778 | D30: Team AWS | E30: Gonzalo Rodriguez | F30: REQ | G30: Configuración Palo Alto Firewall PAN HA | H30: Avances de configuración
B31: 45796 | C31: 45778 | D31: Team AWS | E31: Gonzalo Rodriguez | F31: REQ | G31: AWS Landing Zone Fase 2 | H31: Sesion de Levantamiento
B32: 45796 | C32: 45778 | D32: Carlos Villanueva | E32: Gonzalo Rodriguez | F32: REQ | G32: Revision App service Azure | H32: Troubleshooting app service cnormativo-be
B33: 45797 | C33: 45778 | D33: Team AWS | E33: Gonzalo Rodriguez | F33: REQ | G33: AWS Landing Zone Fase 2 | H33: Sesion de Levantamiento
B34: 45799 | C34: 45778 | D34: Luz Rivera | E34: Gonzalo Rodriguez | F34: REQ | G34: Revision performance app service | H34: Reinicio y escalamiento horizontal de plan ASEWIN02 para proceso en sdm-back
... B295: 46091 | C295: 46082 | D295: Jorge Echeñique | E295: Gonzalo Rodriguez | F295: REQ | G295: Pruebas Api Gateways cuenta SrvTransversales | H295: Ejecución de pruebas Api Gateway Pisee Notificador
B296: 46092 | C296: 46082 | D296: Fabian Flores | E296: Gonzalo Rodriguez | F296: REQ | G296: Habilitacion de permisos en Storage Account | H296: Habilitacion de permisos Reader en Storage Account: almacenexpedienteafdev a ffloresl.srv@ips.gob.cl | I296: Finalizado | J296: 1 hr
B297: 46092 | C297: 46082 | D297: Jorge Echeñique | E297: Gonzalo Rodriguez | F297: REQ | G297: Pruebas Api Gateways cuenta SrvTransversales | H297: Ejecución de pruebas Api Gateway Pisee Notificador | I297: Finalizado | J297: 4 hr
B298: 46093 | C298: 46082 | D298: Jorge Echeñique - Marco | E298: Gonzalo Rodriguez | F298: REQ | G298: Api Gateways cuenta SrvTransversales | H298: Correccion de la Ejecución de pruebas Api Gateway Pisee Notificador | I298: Finalizado | J298: 3 hr
B299: 46093 | C299: 46082 | D299: Andres Bastias | E299: Gonzalo Rodriguez | F299: REQ | G299: Azure App service pensionfem | H299: Resivión de Informe Ciberseguridad Hacking Etico App service Pensionfem | I299: Finalizado | J299: 3 hr
B300: 46094 | C300: 46082 | D300: Paola Lillo | E300: Gonzalo Rodriguez | F300: REQ | G300: Azure App service pensionfem | H300: Se evalua solución para exponer api desde Azure api manager | I300: Finalizado | J300: 1 hr
B301: 46096 | C301: 46082 | D301: Daniel Zamora | E301: Gonzalo Rodriguez | F301: REQ | G301: Actualización minisitio aportefamiliar.cl | H301: Se actualiza codigo fuente a repositorio gitlab en ramas qa y prod | I301: Finalizado | J301: 2 hr
B302: 46097 | C302: 46082 | D302: Andres Bastias | E302: Gonzalo Rodriguez | F302: REQ | G302: Azure App service pensionfem | H302: Se evalua solución para exponer api desde Azure api manager | I302: Finalizado | J302: 2 hr
B303: 46098 | C303: 46082 | D303: Mauricio Miranda | E303: Gonzalo Rodriguez | F303: REQ | G303: Azure Reglas Network Security Group | H303: Se solicita regla para denegar servicios desde NSG de subnet tanzu a base de datos sql (tanzu-mgmt-cluster-node-nsg) solo puerto 443 | I303: Finalizado | J303: 1 hr
B304: 46099 | C304: 46082 | D304: Mauricio Miranda | E304: Gonzalo Rodriguez | F304: REQ | G304: Azure Reglas Network Security Group | H304: Se solicita regla para denegar servicios desde NSG de subnet tanzu a base de datos sql (tanzu-mgmt-cluster-node-nsg) todos los puertos | I304: Finalizado | J304: 1 hr
B305: 46099 | C305: 46082 | D305: Cesar Neculman | E305: Gonzalo Rodriguez | F305: REQ | G305: Propuesta APIM para pensionfem | H305: Se entrega propuesta para exponer api pensionfem desde Azure api manager. | I305: Finalizado | J305: 1 hr
B306: 46100 | C306: 46082 | D306: Gonzalo Rodriguez | E306: Gonzalo Rodriguez | F306: REQ | G306: Pruebas Api Gateways cuenta SrvTransversales | H306: Revisión y correcciones api managment pisee notificador | I306: Finalizado | J306: 4 hr
B307: 46101 | C307: 46082 | D307: Luz Riverea | E307: Gonzalo Rodriguez | F307: REQ | G307: Agregar regla cors Azure app service Productivo | H307: Se agrega cors app service sdm.ips.gob.cl (back y front) | I307: Finalizado | J307: 1 hr
... B321: 46108 | C321: 46143 | D321: Mauro Aprea | E321: Gonzalo Rodriguez | F321: REQ | G321: Despliegue IAC SrvTransversales | H321: Se modela nueva infraestructura desde terraform para api gateway pisee Laboral QA | I321: Finalizado | J321: 1 hr

Sheet OscarMora
B1: FECHA SOLICITUD | C1: Periodo | D1: AREA / PERSONAL SOLICITANTE | E1: PROFESIONAL | F1: INC / REQ / WARNING | G1: Actividad | H1: Detalle / Observación | I1: Estado (en proceso, pendiente, finalizado) | J1: Tiempo estimado actividad | K1: HH EE
B2: 45747 | C2: =IF(B2<>"",B2,"") -> 45747 | D2: Gonzalo Sepulveda | E2: Oscar Mora | F2: REQ | G2: Revisión en linea de logs por falla en una función del aplicativo
B3: 45749 | C3: 45748 | D3: Gonzalo Sepulveda | E3: Oscar Mora | F3: REQ | G3: Revisión de SR por falla en subida de algunos archivos
B4: 45750 | C4: 45748 | D4: Gonzalo Sepulveda | E4: Oscar Mora | F4: REQ | G4: Reinicio de nodos y agente de ODI
B5: 45751 | C5: 45748 | D5: IPS en Linea | E5: Oscar Mora | F5: INC | G5: Falla en IPS en linea: Post aplicación de parchado de seguridad | H5: Se restaura un FS por parte de AWS, se reinician plataformas y hay problema con osbprod01 para iniciar sistema
B6: 45754 | C6: 45748 | D6: IPS en Linea | E6: Oscar Mora | F6: REQ | G6: Mantenimiento Programado - Servicio WebLogic - Lunes 07 de Abril - 18:00 Hrs | H6: Se realiza en el servidor 10.150.150.103 | K6: 2
B7: 45755 | C7: 45748 | D7: PFP | E7: Oscar Mora | F7: INC | G7: Problema con app | H7: Fallo en nodo 1 y 2
B8: 45755 | C8: 45748 | D8: Jorge Eheñique | E8: Oscar Mora | F8: INC | G8: problema en un servicio que consume el ohs, desde ayer en la tarde esta abajo, el mismo servicio de siempre; http://ohsprod01.ips.gob.cl:7777/CLAT/HP/v1_0/HistoricoPrevisional?wsdl | H8: Maquina no respondía por ssh, se escala con Infra para su apoyo. Infra revisa y faltaba un check (de 2) en inicio. Se procede a reiniciar la maquina (AWS - Sao Pablo) - Demoró en iniciar pero quedó arriba
B9: 45755 | C9: 45748 | D9: Portal de Pago | E9: Oscar Mora | F9: REQ | G9: Reunión con Oracle por problema de certificado en OHS | H9: Reunión de trabajo
B10: 45757 | C10: 45748 | D10: Portal de Pago | E10: Oscar Mora | F10: REQ | G10: Iteración con Oracle por SR SR 3-40360525901 | H10: Problem in the OHS which when loading a file of any size between 2 to 700 MB which gives us a connect
B11: 45758 | C11: 45748 | D11: Portal de Pago | E11: Oscar Mora | F11: REQ | G11: Reunión con Oracle por problema de certificado en OHS | H11: Reunión de trabajo
B12: 45758 | C12: 45748 | D12: Portal de Pago | E12: Oscar Mora | F12: REQ | G12: Iteración con Oracle por SR SR 3-40360525901 | H12: Problem in the OHS which when loading a file of any size between 2 to 700 MB which gives us a connect
B13: 45762 | C13: 45748 | D13: PFP | E13: Oscar Mora | F13: INC | G13: Sistema PFP no funciona | H13: Nodos: 1 y 3 con falla. Se realiza reinicio sanitario controlado, recuperando la plataforma
B14: 45762 | C14: 45748 | D14: Portal de Pago | E14: Oscar Mora | F14: REQ | G14: Reunión de entrega PDP
B15: 45762 | C15: 45748 | D15: PFP | E15: Oscar Mora | F15: REQ | G15: Reunion Informativa PFP y Otros | H15: a razón de las multiples fallas de pfp en estas 2 semanas
B16: 45762 | C16: 45748 | D16: Portal de Pago | E16: Oscar Mora | F16: REQ | G16: Iteración con Oracle por SR SR 3-40360525901 | H16: Problem in the OHS which when loading a file of any size between 2 to 700 MB which gives us a connect
B17: 45763 | C17: 45748 | D17: Portal de Pago | E17: Oscar Mora | F17: REQ | G17: Instalación properties en PRD | H17: Ejecución según lo indicado en el documento FINS - Ticket 14634
B18: 45768 | C18: 45748 | D18: PFP | E18: Oscar Mora | F18: INC | G18: Sistema PFP no funciona | H18: Servidor con problemas de espacio en el /u01, por lo que no funcionaba nodos 1 y 3
B19: 45768 | C19: 45748 | D19: Portal de Pago | E19: Oscar Mora | F19: REQ | G19: Iteración con Oracle por SR SR 3-40360525901 | H19: Problem in the OHS which when loading a file of any size between 2 to 700 MB which gives us a connect
B20: 45768 | C20: 45748 | D20: Gonzalo Sepulveda | E20: Oscar Mora | F20: REQ | G20: Configuración https en OHS DEV | H20: Se reconfiguran archivos de sistema OHS para que tomaran
B21: 45768 | C21: 45748 | D21: Gonzalo Sepulveda | E21: Oscar Mora | F21: INC | G21: No se puede conectar al portal de pago de DEV | H21: Problema con su equipo, el cual no tenia acceso por reglas de FW
B22: 45768 | C22: 45748 | D22: Gonzalo Sepulveda | E22: Oscar Mora | F22: REQ | G22: Portal de Pago PROD: Se suben archivos a procesar | H22: Falla nuevamente por OHS, se capturan videos para subir al SR con Oracle por issue
B23: 45768 | C23: 45748 | D23: Portal de Pago | E23: Oscar Mora | F23: REQ | G23: Iteración con Oracle por SR SR 3-40360525901 | H23: Se itera SR, respondiendo lo consultado y se suben videos de lo realizado en falla de subida de archivos en PdP PROD
B24: 45769 | C24: 45748 | D24: Gonzalo Sepulveda | E24: Oscar Mora | F24: REQ | G24: OHS DEV creación de usuario para Claudio Oyarzun | H24: Usuario existía, solo se resetea la pass y se realizan pruebas de acceso y ejecución de procesos en plataforma
B25: 45770 | C25: 45748 | D25: PFP | E25: Oscar Mora | F25: INC | G25: Sistema PFP no funciona | H25: Nodo 1 con problemas, se reinicia y se recupera el sistema.
B26: 45771 | C26: 45748 | D26: PFP | E26: Oscar Mora | F26: INC | G26: Sistema PFP no funciona | H26: Nodo 1 con problemas, se reinicia y se recupera el sistema.
... B33: 45776 | C33: 45748 | D33: ASIMU | E33: Oscar Mora | F33: INC | G33: No se puede accedes al sistema ASIMU | H33: Se reinicia los nodos del wls y queda operativo
B34: 45777 | C34: 45748 | D34: ASIMU | E34: Oscar Mora | F34: INC | G34: Falla en Solicitud Asignación por Muerte/Cuota Mortuoria - Empresas | H34: Antes de presentar problemas Informix, falla en lentitud de despliegue | K34: todo el día
B35: 45777 | C35: 45748 | D35: AFPER | E35: Oscar Mora | F35: REQ | G35: Paso a producción AFPER Urgente | H35: ticket 14780
B36: 45778 | C36: 45778 | D36: ASIMU | E36: Oscar Mora | F36: INC | G36: Sigue falla en Solicitud Asignación por Muerte/Cuota Mortuoria - Empresas | H36: El problema estaba en url ssl a papperless (Sergio Santibañez) el 30 de abril de la suceso dieron de baja una url http://siagf.paperless.cl, debian cambiar los desarrollos a http://ws.pias.suseso.cl/ eso le pega a facilita. van a mandar un comunicado informando que el problema se mantendrá el lunes mientras trabajan en la solución | K36: todo el día
B37: 45782 | C37: 45778 | D37: Gonzalo Sepulveda | E37: Oscar Mora | F37: REQ | G37: Ticket 14792: reiniciar los nodos de ODI PRD e iniciar el plan de carga | H37: se realiza lo solicitado
B38: 45782 | C38: 45778 | D38: Gonzalo Sepulveda | E38: Oscar Mora | F38: INC | G38: Problemas con el procesamiento de planes de carga | H38: Era solo lentitud en BD, por la alta carga
B39: 45782 | C39: 45778 | D39: Victor Caroca | E39: Oscar Mora | F39: REQ | G39: Ayuda con datos de unos datasource de bpel. Son estos dos: eis/DB/Facilita_Afper y eis/DB/Facilita_Informix | H39: se realiza lo solicitado
B40: 45782 | C40: 45778 | D40: Victor Caroca | E40: Oscar Mora | F40: REQ | G40: buscar el datasource Facilita_CoreAgil, en productivo
B41: 45782 | C41: 45778 | D41: Victor Caroca | E41: Oscar Mora | F41: REQ | G41: Solicitud de configuraciones de la carpeta IPS_HOME\appl
B42: 45783 | C42: 45778 | D42: Priscilla Valenzuela | E42: Oscar Mora | F42: INC | G42: Reunión configuraciones, revision logs, realizar pruebas | H42: Todo el día en encontrar solución con el área de ChileAtiende
B43: 45784 | C43: 45778 | D43: Priscilla Valenzuela | E43: Oscar Mora | F43: INC | G43: Reunión configuraciones, revision logs, realizar pruebas | H43: La solución se implementor parte de la gente de desarrollo del área de ChileAtiende.
B44: 45786 | C44: 45778 | D44: Daniel Zamora | E44: Oscar Mora | F44: INC | G44: Problemas en osb afper | H44: estaba pegado y la consola de admin no respondía
B45: 45786 | C45: 45778 | D45: Daniel Zamora | E45: Oscar Mora | F45: INC | G45: Falla en servicio del BUS AFPProject, por problemas en respuesta | H45: Arrojaba en los logs socket timeout en servicio AFPProject, ya que estaba direccionando http://siagf.paperless.cl, y debe ser ahora a pias.suceso.cl. Problema solucionado con paso a prod de nuevo componente. Quedó con errores pero operativo. Daniel Zamora enviará correo con detalles y compromiso de eliminar los logs. | K45: todo el día
B46: 45803 | C46: 45778 | D46: Priscilla Valenzuela | E46: Oscar Mora | F46: REQ | G46: Reunión: Estrategia bajada ipsenlinea
B47: 45804 | C47: 45778 | D47: Gonzalo Sepulveda | E47: Oscar Mora | F47: REQ | G47: Reunión: OHS - Redireccionamiento de http a https | H47: Explicación de como está funcionando y como mejorar la config en los distintos ambientes
B48: 45805 | C48: 45778 | D48: Nicolas Galarce | E48: Oscar Mora | F48: INC | G48: Ticket: Problemas con PFP, aplicativo no carga | H48: Problemas con nodo 1 (puerto 9001).
B49: 45807 | C49: 45778 | D49: Paola Lillo | E49: Oscar Mora | F49: INC | G49: El servidor 10.150.226.95 está sin espacio disponible | H49: Se libera espacio, quedando con 90% disponible
B50: 45807 | C50: 45778 | D50: Patricio Ordenes | E50: Oscar Mora | F50: REQ | G50: Entregar los registros log de hoy (29-05-2025), ubicados en la ruta $IPS_HOME/appl/sgi-rechazobancario/logs | H50: Se entrega lo solicitado
B51: 45807 | C51: 45778 | D51: Priscilla Valenzuela | E51: Oscar Mora | F51: REQ | G51: Reunión: Redirección o bajada URL ipsenlinea | H51: Reconfiguración de archivo mod_wl_ohs.conf para redireccionamiento para persona y empresa
B52: 45807 | C52: 45778 | D52: Patricio Ordenes | E52: Oscar Mora | F52: INC | G52: Problemas con sitio web gestion.ipsenlinea.cl | H52: Se realiza vuelta atrás del archivo mod_wl_ohs.conf y queda operativo
B53: 45810 | C53: 45809 | D53: Gonzalo Sepulveda | E53: Oscar Mora | F53: REQ | G53: Ticket 15091: Instalación en SIT (QA)
B54: 45813 | C54: 45809 | D54: Victor Caroca | E54: Oscar Mora | F54: INC | G54: problema con los servicios facilita, puedes revisar que el soa este funcionando en productivo | H54: /BEN/Facilita/v1_0/ConsultarBeneficios
B55: 45817 | C55: 45809 | D55: Carlos Jara | E55: Oscar Mora | F55: INC | G55: Problemas con alertas de Weblogic en PdP | H55: Se revisa toda la plataforma y no se detecta problemas asociados a la alerta. Siguen escalando y se revisa nuevamente con igual observación
B56: 45818 | C56: 45809 | D56: Gonzalo Sepulveda | E56: Oscar Mora | F56: REQ | G56: Necesita PortalPagoWeb.properties de Produccion | H56: Se entrega lo solicitado
B57: ??? | C57: ???
B58: ??? | C58: ???
B59: ??? | C59: ???
B60: 45826 | C60: 45809 | D60: Gonzalo Sepulveda | E60: Oscar Mora | F60: REQ | G60: reunión con Oracle por SR abierto por falla en subida de archivos | H60: se capturan evidencias y logs para subir al SR
B61: 45831 | C61: 45809 | D61: Monitoreo / NOC | E61: Oscar Mora | F61: INC | G61: AFPER: PROD - Alertas por indisponibilidad de Admin y nodo OSB | H61: Se levanta servicio y nodo
B62: 45832 | C62: 45809 | D62: Gonzalo Sepulveda | E62: Oscar Mora | F62: REQ | G62: Iteración con Oracle por SR SR 3-40360525901 | H62: Problem in the OHS which when loading a file of any size between 2 to 700 MB which gives us a connect
B63: 45832 | C63: 45809 | D63: Victor Caroca | E63: Oscar Mora | F63: INC | G63: Sistema weblogic abajo en DEV | H63: Se levanta servicio y nodo
B64: 45832 | C64: 45809 | D64: NOC | E64: Oscar Mora | F64: INC | G64: Reportan mas de 12 alertas de monitoreo asociado a weblogic | H64: Se revisa plataforma y la mayoria eran falsos positivos. Habian 2 que estaban caidos (consolas)
B65: 45833 | C65: 45809 | D65: Cesar Neculman | E65: Oscar Mora | F65: INC | G65: PROD: No permite desplegar combo box de mes y año | H65: Se revisa la plataforma de Portal de Pago y se encuentra que el OHS, nodo 2, estaba abajo. Se sube y recupera incidente
B66: 45834 | C66: 45809 | D66: Cesar Neculman | E66: Oscar Mora | F66: REQ | G66: Iteración con Oracle por SR SR 3-40360525901 | H66: Se realiza agregación de parametros en httpd.conf, y hay que probar el funcionamiento de procesamiento de archivos.
B67: 45835 | C67: 45809 | D67: Cesar Neculman | E67: Oscar Mora | F67: REQ | G67: Iteración con Oracle por SR SR 3-40360525901 | H67: Se realiza agregación de parametros en httpd.conf, y hay que probar el funcionamiento de procesamiento de archivos.
B68: 45839 | C68: 45839 | D68: Cesar Neculman | E68: Oscar Mora | F68: REQ | G68: Iteración con Oracle por SR SR 3-40360525901 | H68: Se realiza agregación de parametros en httpd.conf, y hay que probar el funcionamiento de procesamiento de archivos.
B69: 45840 | C69: 45839 | D69: Paola Lillo | E69: Oscar Mora | F69: INC | G69: Alerta en servidor bpmqa1 (10.150.226.212), problema espacio en / | H69: Se livera 4%, recomendando aumentar espacio en FS /
B70: 45840 | C70: 45839 | D70: Jorge Eheñique | E70: Oscar Mora | F70: INC | G70: problema al consumir http://ohsprod01.ips.gob.cl:7777/CLAT/HP/v1_0/HistoricoPrevisional?wsdl | H70: Servidor osb no puede conectarse al ohs1, al puerto 7777
B71: 45841 | C71: 45839 | D71: Nicolas Reyes | E71: Oscar Mora | F71: REQ | G71: Reunión Incidentes en ASIMU | H71: Apoyo tecnico
B72: 45842 | C72: 45839 | D72: Oscar Mora | E72: Oscar Mora | F72: INC | G72: IPS: Reinicio preventivo de los nodos OHS | H72: Aplicación con problemas
B73: 45843 | C73: 45839 | D73: Patricio Ramirez | E73: Oscar Mora | F73: INC | G73: Problemas post DRP Legados falla ASIMU | H73: No esta clara la falla y se revisa la plataforma y presta apoyo en una reunión por incidente | K73: 7 HH extras
B74: 45845 | C74: 45839 | D74: Jesus Chavez | E74: Oscar Mora | F74: INC | G74: Revisar alerta de monitoreo servidor bpmprod01.ips.gob.cl | H74: Puertos estaban alertados, pero al revisar la plataforma estaba todo funcionando correctamente.
B75: 45848 | C75: 45839 | D75: Patricio Ramirez | E75: Oscar Mora | F75: REQ | G75: Reunión: Análisis y Coordinación Incidente Notificación a SUPEN - NOC - DC - SOC
B76: 45853 | C76: 45839 | D76: Cesar Neculman | E76: Oscar Mora | F76: REQ | G76: Iteración con Oracle por SR SR 3-40360525901 | H76: Problem in the OHS which when loading a file of any size between 2 to 700 MB which gives us a connect
B77: 45855 | C77: 45839 | D77: Cesar Neculman | E77: Oscar Mora | F77: REQ | G77: reunión con Oracle por SR abierto por falla en subida de archivos | H77: se capturan evidencias y logs para subir al SR, ya que la prueba falló
B78: 45856 | C78: 45839 | D78: Cesar Neculman | E78: Oscar Mora | F78: REQ | G78: Iteración con Oracle por SR SR 3-40360525901 | H78: Se suben evidencias de las pruebas realizadas ayer
B79: 45856 | C79: 45839 | D79: Patricio Ramirez | E79: Oscar Mora | F79: INC | G79: Alerta en monitoreo http://ohsprod01.ips.gob.cl:7777/CLAT/HP/v1_0/HistoricoPrevisional?wsdl | H79: Se realiza reunión con multiples áreas y se detecta que habían aplicado una regla en el FW que bloqueó acceso de prooosb02 a ohs, puerto 7777
B80: 45859 | C80: 45839 | D80: Juan Pablo Buzeta | E80: Oscar Mora | F80: INC | G80: PRD-AFPER-OSB - 10.200.13.250 - puerto 7001 alertado | H80: Se reinicia el servicio de weblogic (consola) y este problema no afecta servicio.
B81: 45859 | C81: 45839 | D81: Claudio Balbontin | E81: Oscar Mora | F81: INC | G81: Aplicativo no está tomando archivos desde el FTP | H81: ticket
B82: 45860 | C82: 45839 | D82: Oscar Mora | E82: Oscar Mora | F82: REQ | G82: Reinicio preventivo PFP PROD | H82: se realiza a las 8 AM
B83: 45861 | C83: 45839 | D83: Oscar Mora | E83: Oscar Mora | F83: REQ | G83: Reinicio preventivo PFP PROD | H83: se realiza a las 8 AM
B84: 45861 | C84: 45839 | D84: Cesar Neculman | E84: Oscar Mora | F84: REQ | G84: Iteración con Oracle por SR SR 3-40360525901 | H84: Se realiza agregación de parametros en httpd.conf, y hay que probar el funcionamiento de procesamiento de archivos.
B85: 45861 | C85: 45839 | D85: Cesar Neculman | E85: Oscar Mora | F85: INC | G85: BPM está lento | H85: Consola y nodos no respondian, a pesar de estár funcionando.
B86: 45862 | C86: 45839 | D86: Oscar Mora | E86: Oscar Mora | F86: REQ | G86: Reinicio preventivo PFP PROD | H86: se realiza a las 8 AM
B87: 45863 | C87: 45839 | D87: Paola Lillo | E87: Oscar Mora | F87: INC | G87: Alerta de espacio en root | H87: se pudo dejar en 94% libre, por lo cual se sugiere aumentar el tamaño del file system
B88: 45863 | C88: 45839 | D88: Cesar Neculman | E88: Oscar Mora | F88: REQ | G88: Iteración con Oracle por SR SR 3-40360525901 | H88: Se realiza agregación de parametros en httpd.conf, y hay que probar el funcionamiento de procesamiento de archivos.
B89: 45866 | C89: 45839 | D89: Jorge Eheñique | E89: Oscar Mora | F89: REQ | G89: Apoyo para buscar servicios homologos de QA en PROD
B90: 45867 | C90: 45839 | D90: Patricio Ordenes | E90: Oscar Mora | F90: INC | G90: Ayuda para restablecer los servicios del server http://10.150.226.95/ | H90: Ambiente QA - Se valida espacio y memoria y esta todo bien. Se reinicia el nodo nuevamente (18 hrs)
B91: 45868 | C91: 45839 | D91: Patricio Ordenes | E91: Oscar Mora | F91: INC | G91: Apoyo con servidor http://10.150.226.95// 15598 | H91: Problemas con DS: 15 servidores no responden a test de conexión desde 10.150.226.95. Servidores no existen, nadie sabe si sirven esas conexiones a las BD
B92: 45868 | C92: 45839 | D92: Nicolas Reyes | E92: Oscar Mora | F92: INC | G92: Reunión: cambio forma de pago / servicios abajo | H92: Fue una War room y también se revisó el problema de la 226.95. Terminamos pasado las 18:15 hrs
B93: 45870 | C93: 45870 | D93: Nicolas Reyes | E93: Oscar Mora | F93: INC | G93: Iteración Problema: Apoyo con servidor http://10.150.226.95// 15598
B94: 45870 | C94: 45870 | D94: Ricardo Orellana | E94: Oscar Mora | F94: REQ | G94: Conexiones que van desde osbprod01.ips.gob.cl a las BD | H94: se saca un listado y se envía por teams
B95: 45870 | C95: 45870 | D95: Cesar Neculman | E95: Oscar Mora | F95: REQ | G95: Iteración con Oracle por SR SR 3-40360525901
B96: 45870 | C96: 45870 | D96: Nicolas Reyes | E96: Oscar Mora | F96: INC | G96: Iteración Problema: Apoyo con servidor http://10.150.226.95// 15598
B97: 45870 | C97: 45870 | D97: Ricardo Orellana | E97: Oscar Mora | F97: REQ | G97: Conexiones que van desde osbprod01.ips.gob.cl a las BD | H97: se saca un listado y se envía por teams
B98: 45870 | C98: 45870 | D98: Cesar Neculman | E98: Oscar Mora | F98: REQ | G98: Iteración con Oracle por SR SR 3-40360525901
B99: 45873 | C99: 45870 | D99: Juan Pablo Buzeta | E99: Oscar Mora | F99: INC | G99: Incidente en Server PRD-AFPER-OSB - 10.200.13.250 | H99: Problena con el puerto 7001, no respondía
D100: ?? | G100: Reunion
B101: 45880 | C101: 45870 | D101: Cesar Neculman | E101: Oscar Mora | F101: INC | G101: Reunión con Oracle: Continuidad Problema de EM y OHS de PdP | H101: Se continuan los trabajos que quedaron pendientes desde el viernes, que fue el control de los nodos por EM
B102: 45881 | C102: 45870 | D102: Cesar Neculman | E102: Oscar Mora | F102: INC | G102: Reunión con Oracle: Continuidad Problema de EM y OHS de PdP | H102: Ayer no se pudo corregir el problema del control de los nodos por EM, y hoy se continuan los trabajos
D103: ???
D104: ???
B105: 45901 | C105: 45901 | D105: Oracle Middleware | E105: Oscar Mora | F105: REQ | G105: IPS-Oracle: levantamiento Middleware | H105: Copia de archivos para hacer levantamiento en plataforma Oracle Middleware IPS
B106: 45902 | C106: 45901 | D106: Oracle Middleware | E106: Oscar Mora | F106: REQ | G106: IPS-Oracle: levantamiento Middleware | H106: Copia de archivos para hacer levantamiento en plataforma Oracle Middleware IPS
...

Sheet GabrielNuñez
B1: FECHA SOLICITUD | C1: Periodo | D1: AREA / PERSONAL SOLICITANTE | E1: PROFESIONAL | F1: INC / REQ / WARNING | G1: Actividad | H1: Detalle / Observación | I1: Estado (en proceso, pendiente, finalizado) | J1: Tiempo estimado actividad
B2: 45726 | C2: 09:00 - 18:00 | D2: Operaciones | E2: Jose Luis Hernandez | F2: REQ | G2: Gestión y prueba de accesos
B3: 45727 | C3: 09:00 - 18:00 | D3: Operaciones | E3: Jose Luis Hernandez | F3: REQ | G3: Gestión y prueba de accesos
B4: 45728 | C4: 09:00 - 18:00 | D4: Operaciones | E4: Jose Luis Hernandez | F4: REQ | G4: Gestión y prueba de accesos
B5: 45729 | C5: 09:00 - 18:00 | D5: Operaciones | E5: Patricio Ramirez | F5: INC | G5: Reunión sobre caídas del servidor BD
B6: 45730 | C6: 09:00 - 18:00 | D6: DYM | E6: Jorge León | F6: INC | G6: Revisión de repositorios ODI
B7: 45733 | C7: 09:00 - 18:00 | D7: DYM | E7: Jorge León | F7: INC | G7: Revisión de repositorios ODI
B8: 45734 | C8: 09:00 - 18:00 | D8: DYM | E8: Jorge León | F8: INC | G8: Revisión de repositorios ODI
B9: 45735 | C9: 09:00 - 18:00 | D9: DYM | E9: Jorge León | F9: INC | G9: Revisión de repositorios ODI
B10: 45736 | C10: 09:00 - 18:00 | D10: DYM | E10: Jorge León | F10: INC | G10: Revisión de repositorios ODI
B11: 45737 | C11: 09:00 - 18:00 | D11: DYM | E11: Jorge León | F11: INC | G11: Planificación migración repositorios
B12: 45740 | C12: 09:00 - 18:00 | D12: DYM | E12: Jorge León | F12: INC | G12: Revisión de requisitos para migrar repositorios
B13: 45741 | C13: 09:00 - 18:00 | D13: DYM | E13: Jorge León | F13: INC | G13: Revisión de requisitos para migrar repositorios
... B195: 46000 | C195: 09:00 - 18:00 | D195: INFRAESTRUCTURA | E195: PAOLA LILLO | F195: REQ | G195: PROYECTO LANDING ZONE, AFPER
B196: 46001 | C196: 09:00 - 18:00 | D196: DYM | E196: JORGE LEÓN | F196: INC | G196: INCIDENCIAS ODI ELEGIBILIDAD | H196: Se realiza informe respectivo
B197: 46002 | C197: 09:00 - 18:00 | D197: DYM | E197: JORGE LEÓN | F197: Alerta | G197: REVISIÓN ODI, STAGING PRODUCCIÓN | H197: Es un seguimiento al incidente del día anterior
B198: 46003 | C198: 09:00 - 18:00 | D198: INGENIERIA | E198: PATRICIO RAMIREZ | F198: REQ | G198: MEJORAS SERVIDOR ODI
B199: 46006 | C199: 09:00 - 18:00 | D199: INGENIERIA | E199: PATRICIO RAMIREZ | F199: REQ | G199: MEJORAS SERVIDOR ODI
B200: 46007 | C200: 09:00 - 18:00 | D200: INGENIERIA | E200: PATRICIO RAMIREZ | F200: REQ | G200: MEJORAS SERVIDOR ODI
B201: 46008 | C201: 09:00 - 18:00 | D201: INGENIERIA | E201: PATRICIO RAMIREZ | F201: REQ | G201: MEJORAS SERVIDOR ODI
B202: 46009 | C202: 09:00 - 18:00 | D202: INGENIERIA | E202: PATRICIO RAMIREZ | F202: REQ | G202: MEJORAS SERVIDOR ODI
B203: 46010 | C203: 09:00 - 18:00 | D203: INGENIERIA | E203: PATRICIO RAMIREZ | F203: REQ | G203: MEJORAS SERVIDOR ODI
B204: 46013 | C204: 09:00 - 18:00 | D204: INGENIERIA | E204: PATRICIO RAMIREZ | F204: REQ | G204: MEJORAS SERVIDOR ODI
B205: 46014 | C205: 09:00 - 18:00 | D205: INGENIERIA | E205: PATRICIO RAMIREZ | F205: REQ | G205: MEJORAS SERVIDOR ODI
B206: 46015 | C206: 09:00 - 18:00 | D206: INGENIERIA | E206: PATRICIO RAMIREZ | F206: REQ | G206: MEJORAS SERVIDOR ODI
B207: 46017 | C207: 09:00 - 18:00 | D207: DYM | E207: CHRISTIAN ROJAS | F207: INC | G207: ERROR ODI PRODUCCIÓN, MEMORY HEAP, REINICIO | H207: Se realiza informe repectivo
B208: 46020 | C208: 09:00 - 18:00 | D208: DYM | E208: CHRISTIAN ROJAS | F208: INC | G208: MEJORAS EN LOS PARAMETROS DE ODI EN CLIENTES | H208: Es un seguimiento al incidente del día anterior
B209: 46021 | C209: 09:00 - 18:00 | D209: DYM | E209: CHRISTIAN ROJAS | F209: INC | G209: REVISIÓN DE ESTADO DE LAS EJECUCIONES ODI PRODUCCIÓN | H209: Es un seguimiento al incidente del día anterior
B210: 46022 | C210: 09:00 - 18:00 | D210: INGENIERIA | E210: PATRICIO RAMIREZ | F210: REQ | G210: MEJORAS SERVIDOR ODI
B211: 46024 | C211: 09:00 - 18:00 | D211: DYM | E211: CHRISTIAN ROJAS | F211: INC | G211: MONITOREO MODULO APS Y DMPAGOS | H211: Se reportaba lentitud, pero no se observó nada
B212: 46027 | C212: 09:00 - 18:00 | D212: INGENIERIA | E212: PATRICIO RAMIREZ | F212: REQ | G212: MEJORAS SERVIDOR ODI
B213: 46028 | C213: 09:00 - 18:00 | D213: INGENIERIA | E213: PATRICIO RAMIREZ | F213: REQ | G213: MEJORAS SERVIDOR ODI
B214: 46029 | C214: 09:00 - 18:00 | D214: INGENIERIA | E214: PATRICIO RAMIREZ | F214: REQ | G214: MEJORAS SERVIDOR ODI
B215: 46030 | C215: 09:00 - 18:00 | D215: INGENIERIA | E215: PATRICIO RAMIREZ | F215: REQ | G215: MEJORAS SERVIDOR ODI
B216: 46031 | C216: 09:00 - 18:00 | D216: DYM | E216: CHRISTIAN ROJAS | F216: INC | G216: ERROR ENVIO DE CORREO MÓDULO DMPAGOS | H216: Se presenta informe respectivo.
B217: 46034 | C217: 09:00 - 18:00 | D217: DYM | E217: CHRISTIAN ROJAS | F217: INC | G217: MONITOREO ENVÍO DE CORREOS ODI PRD | H217: Se valida que el cambio realizado no afectó otros módulos. Es un seguimiento al incidente del día anterior.
B218: 46035 | C218: 09:00 - 18:00 | D218: INGENIERIA | E218: PATRICIO RAMIREZ | F218: REQ | G218: MEJORAS SERVIDOR ODI ONPREMISE
B219: 46036 | C219: 09:00 - 18:00 | D219: INGENIERIA | E219: PATRICIO RAMIREZ | F219: REQ | G219: MEJORAS SERVIDOR ODI ONPREMISE
B220: 46037 | C220: 09:00 - 18:00 | D220: DYM | E220: Paola Bustamante | F220: REQ | G220: Soporte pdp subida de archivos | H220: Se valida el funcionamiento y los logs, se detecta que la casilla de correo está full y hay usuarios que no tienen permisos
B221: 46038 | C221: 09:00 - 18:00 | D221: DYM | E221: Paola Bustamante | F221: REQ | G221: Soporte pdp subida de archivos | H221: Se valida el funcionamiento y los logs, se detecta que la casilla de correo está full y hay usuarios que no tienen permisos
B222: 46039 | C222: 09:00 - 18:00 | D222: DYM | E222: Paola Bustamante | F222: REQ | G222: Soporte pdp subida de archivos | H222: Horas extraordinarias 16:00 a 18:00
B223: 46040 | C223: 09:00 - 18:00 | D223: DYM | E223: Paola Bustamante | F223: REQ | G223: Soporte pdp subida de archivos | H223: Horas extraordinarias 15:00 a 18:00
B224: 46041 | C224: 09:00 - 18:00 | D224: DYM | E224: Paola Bustamante | F224: REQ | G224: Soporte pdp subida de archivos
B225: 46042 | C225: 09:00 - 18:00 | D225: DYM | E225: Paola Bustamante | F225: REQ | G225: Soporte pdp dev, ssl
B226: 46043 | C226: 09:00 - 18:00 | D226: DYM | E226: Paola Bustamante | F226: REQ | G226: Soporte pdp dev, ssl
B227: 46044 | C227: 09:00 - 18:00 | D227: DYM | E227: César Neculman | F227: REQ | G227: Revisión PDP SIT https
B228: 46045 | C228: 09:00 - 18:00 | D228: DYM | E228: César Neculman | F228: REQ | G228: Revisión PDP SIT https
B229: 46048 | C229: 09:00 - 18:00 | D229: DYM | E229: Gonzalo Sepúlveda | F229: REQ | G229: Revisión accesos PDP SIT
B230: 46049 | C230: 09:00 - 18:00 | D230: INGENIERIA | E230: PATRICIO RAMIREZ | F230: REQ | G230: MEJORAS SERVIDOR ODI ON PREMISE
B231: 46050 | C231: 09:00 - 18:00 | D231: INGENIERIA | E231: PATRICIO RAMIREZ | F231: REQ | G231: MEJORAS SERVIDORE ODI ON PREMISE
B232: 46051 | C232: 09:00 - 18:00 | D232: DYM | E232: Jorge León | F232: REQ | G232: Revisión preventiva ODI Datos
B233: 46052 | C233: 09:00 - 18:00 | D233: DYM | E233: Jorge León | F233: REQ | G233: Revisión de ODI DAtos prd, procesos detenidos | H233: Se reinicia el dominio, había contención desde bd
B234: 46055 | C234: 09:00 - 18:00 | D234: DYM | E234: Jorge León | F234: REQ | G234: Revisión de ODI Datos PRD, procesos detenidos | H234: Se valida el funcionamiento y los logs
B235: 46056 | C235: 09:00 - 18:00 | D235: Operaciones | E235: Daniel Zamora | F235: REQ | G235: Homologación de nodos afper
B236: 46057 | C236: 09:00 - 18:00 | D236: Operaciones | E236: Daniel Zamora | F236: REQ | G236: Revisión nodos afper
B237: 46058 | C237: 09:00 - 18:00 | D237: Operaciones | E237: Daniel Zamora | F237: REQ | G237: Revisión nodos afper
B238: 46059 | C238: 09:00 - 18:00 | D238: DYM | E238: Paola Bustamante | F238: REQ | G238: Revisión de DEV PDP (pendiente lo de certificado ssl)
B239: 46062 | C239: 09:00 - 18:00 | D239: DYM | E239: Paola Bustamante | F239: REQ | G239: Revisión de DEV PDP (pendiente lo de certificado ssl)
B240: 46063 | C240: 09:00 - 18:00 | D240: DYM | E240: Gonzalo Sepúlveda | F240: REQ | G240: Actualización archivo de Feriados
B241: 46064 | C241: 09:00 - 18:00 | D241: DYM | E241: Gonzalo Sepúlveda | F241: REQ | G241: Revisión de ambiente desarrollo
B242: 46065 | C242: 09:00 - 18:00 | D242: Infraestructura | E242: Paola Lillo | F242: REQ | G242: Revisión de version de kernel de wls java para servidores AWS LZ PDP
B243: 46066 | C243: 09:00 - 18:00 | D243: DYM | E243: Gonzalo Sepulveda | F243: REQ | G243: Revisión de los faltantes del ambiente DEV para lo del SSL
B244: 46069 | C244: 09:00 - 18:00 | D244: infraestructura | E244: Paola Lillo | F244: REQ | G244: Revisión servidores AWS | H244: Revisión de servidores de AFPER Balanceo, revisión de las máquinas a hacer reinició, metadata y
B245: 46070 | C245: 09:00 - 18:00 | D245: DYM | E245: Jorge Leon | F245: WARNING | G245: Revisión agente ODI PRD | H245: Error agente, saturación de conexiones bd
B246: 46071 | C246: 09:00 - 18:00 | D246: DYM | E246: Gonzalo Sepulveda | F246: WARNING | G246: validaciones técnicas de OHS, WLS, OSB, BPM y problemas de configuración incompleta en DEV.
B247: 46072 | C247: 09:00 - 18:00 | D247: infraestructura | E247: Paola Lillo | F247: REQ | G247: Revisión servidores aws lz dev SGI | H247: Revisión conectividad y uso de aplicación
B248: 46073 | C248: 09:00 - 18:00 | D248: infraestructura | E248: Paola Lillo | F248: REQ | G248: Revisión servidores aws lz dev SGI | H248: Revisión conectividad y uso de aplicación
B249: 46076 | C249: 09:00 - 18:00 | D249: infraestructura | E249: Paola Lillo | F249: REQ | G249: Revisión servidor de reclamo afper de aws landing zone
B250: 46077 | C250: 09:00 - 18:00 | D250: Infraestructura | E250: Paola Lillo | F250: REQ | G250: Revisión servidor de reclamo afper de aws landing zone
B251: 46078 | C251: 09:00 - 18:00 | D251: Infraestructura | E251: Paola Lillo | F251: REQ | G251: Revisión servidor de reclamo afper de aws landing zone
B252: 46079 | C252: 09:00 - 18:00 | D252: Infraestructura | E252: Paola Lillo | F252: REQ | G252: Revisión servidores Afper productivos
B253: 46080 | C253: 09:00 - 18:00 | D253: DYM | E253: Jorge León | F253: REQ | G253: Revisión de carga de archivos odi
B258: 46083 | C258: 09:00 - 18:00 | D258: Infraestructura | E258: Paola Lillo | F258: WARNING | G258: Revisión de logs de servidor WLSPROD03 | H258: Revisión de espacio y zipeo de logs
B259: 46084 | C259: 09:00 - 18:00 | D259: Infraestructura | E259: Paola Lillo | F259: WARNING | G259: Revisión de logs de servidor WLSPROD03
B260: 46085 | C260: 09:00 - 18:00 | D260: DYM | E260: Gonzalo Sepulveda | F260: REQ | G260: Revisión de ODI DEV de PDP | H260: Se valida el cambio de password del repositorio
B261: 46086 | C261: 09:00 - 18:00 | D261: Infraestructura | E261: Paola Lillo | F261: REQ | G261: Revisión plan de reinicio metadata afper y ohs
B262: 46087 | C262: 09:00 - 18:00 | D262: Infraestructura | E262: Paola Lillo | F262: REQ | G262: Revisión servidores de afper producción | H262: sacar de balanceador y apagado
B263: 46090 | C263: 09:00 - 18:00 | D263: Infraestructura | E263: Paola Lillo | F263: Warning | G263: Caida de server admin de osb afper | H263: Se valida que no hay causa en los logs de la caida del admin (ya ha pasado) se aumenta el tamaño de la memoria del admin
B264: 46091 | C264: 09:00 - 18:00 | D264: Infraestructura | E264: Paola Lillo | F264: Warning | G264: Revisión de server admin de afper osb | H264: Se elimina del config los datos de arranque por defecto para evitar
B265: 46091 | C265: 09:00 - 18:00 | D265: Infraestructura | E265: Paola Lillo | F265: REQ | G265: Reunión daily aws lz | I265: Estado (en proceso, pendiente, finalizado) | J265: Tiempo estimado actividad | L265: FECHA AUXILIAR | M265: Saldo diario | N265: Saldo diario
B266: 46092 | C266: 09:00 - 18:00 | D266: Infraestructura | E266: Paola Lillo | F266: REQ | G266: Revisión conectividad de proyecto AWS LZ | H266: Se hicieron pruebas de conectividad en el ambiente de OHS DEV y ADMIN OHS para validar que el servidor levanta y se conecta | I266: FINALIZADO | J266: 8 | M266: {=SUMPRODUCT(($J266:$J496)*((--$B266:$B496)=--B266))} -> 8 | N266: 8
B267: 46093 | C267: 09:00 - 18:00 | D267: DYM | E267: Gonzalo Sepúlveda | F267: REQ | G267: Revisión de SSL en DEV | H267: Persisten los problemas en SSL de DEV, DYM desconoce el estado del proyecto | I267: EN PROCESO | J267: 5 | M267: =SUM(J267:J270) -> 8 | N267: =SUM(J267:J270) -> 8
B268: 46093 | C268: 09:00 - 18:00 | D268: Infraestructura | E268: Paola Lillo | F268: REQ | G268: Revisión conectividad de proyecto AWS LZ | H268: Servidores de PDP DEV, pruebas de conectividad y levantado | I268: FINALIZADO | J268: 1
B269: 46093 | C269: 09:00 - 18:00 | D269: Infraestructura | E269: Daniel Zamora | F269: REQ | G269: Revisión politicas de respaldo | H269: Se revisan las politicas de respaldo de servidores de AWS | I269: FINALIZADO | J269: 1
B270: 46093 | C270: 09:00 - 18:00 | D270: Operaciones | E270: Patricio Ramirez | F270: INTERNO | G270: Reunión de grupo | H270: Temas administrativos de abenis | I270: FINALIZADO | J270: 1
B271: 46094 | C271: 09:00 - 18:00 | D271: DYM | E271: Gonzalo Sepúlveda | F271: REQ | G271: Revisióón de SSL de DEV | H271: Se revisa la configuración de SIT y se replica en DEV, solo en OHS, rutinas de validación | I271: EN PROCESO | J271: 5 | M271: =SUM(J271:J273) -> 8
B272: 46094 | C272: 09:00 - 18:00 | D272: Infraestructura | E272: Paola Lillo | F272: REQ | G272: Uptime y validación de servidores afper | H272: Se valida que levantaron correctamente los siguientes servidores: prd-afper-4, prd-afper-5, prd-afper6 | I272: FINALIZADO | J272: 1
B273: 46094 | C273: 09:00 - 18:00 | D273: DYM | E273: Jorge Leon | F273: REQ | G273: Revisión preventiva ambiente prd de ODI (recepción de archivos). | H273: =G273 -> Revisión preventiva ambiente prd de ODI (recepción de archivos). | I273: FINALIZADO | J273: 2
B274: 46097 | C274: 09:00 - 18:00 | D274: DYM | E274: Gonzalo Sepúlveda | F274: REQ | G274: Revisión de SSL de DEV | H274: Se mantiene un error de redirect del ohs, se determinan problemas del BPM | I274: EN PROCESO | J274: 8 | M274: 8
B275: 46098 | C275: 09:00 - 18:00 | D275: NO APLICA | E275: NO APLICA | F275: INTERNO | G275: Reunión abenis | H275: =G275 -> Reunión abenis | I275: FINALIZADO | J275: 1 | M275: =SUM(J275:J278) -> 8
B276: 46098 | C276: 09:00 - 18:00 | D276: INFRAESTRUCTURA | E276: Paola Lillo | F276: REQ | G276: Reunión daily aws lz | H276: =G276 -> Reunión daily aws lz | I276: FINALIZADO | J276: 1
B277: 46098 | C277: 09:00 - 18:00 | D277: INFRAESTRUCTURA | E277: Paola Lillo | F277: REQ | G277: Reunión sprint de aws lz | H277: =G277 -> Reunión sprint de aws lz | I277: FINALIZADO | J277: 1
B278: 46098 | C278: 09:00 - 18:00 | D278: DYM | E278: Gonzalo Sepúlveda | F278: REQ | G278: Revisión de logs de SSL de DEV | H278: Revisión del error para preparar informe | I278: EN PROCESO | J278: 5
B279: 46099 | C279: 09:00 - 18:00 | D279: CPP | E279: Carlos Salamanca | F279: REQ | G279: Revisión Paso a Producción SGI | H279: =G279 -> Revisión Paso a Producción SGI | I279: FINALIZADO | J279: 2 | M279: =SUM(J279:J280) -> 8
B280: 46099 | C280: 09:00 - 18:00 | D280: DYM | E280: Gonzalo Sepúlveda | F280: REQ | G280: Revisión de SSL de DEV | H280: Se continúa con la revisión del problema, el BPM tiene tiempo sin funcionar | I280: EN PROCESO | J280: 6
B281: 46100 | C281: 09:00 - 18:00 | D281: INFRAESTRUCTURA | E281: Paola Lillo | F281: REQ | G281: Reunión daily aws lz | H281: =G281 -> Reunión daily aws lz | I281: FINALIZADO | J281: 1 | M281: =SUM(J281:J283) -> 8
B282: 46100 | C282: 09:00 - 18:00 | D282: INGENIERIA | E282: Patricio Ramirez | F282: REQ | G282: Reunión de área | H282: Reunión de área de middleware | I282: FINALIZADO | J282: 1
B283: 46100 | C283: 09:00 - 18:00 | D283: CPP | E283: Carlos Salamanca | F283: REQ | G283: Paso a producción SGI | H283: =G283 -> Paso a producción SGI | I283: FINALIZADO | J283: 6
B284: 46101 | C284: 09:00 - 18:00 | D284: INGENIERIA | E284: Patricio Ramirez | F284: REQ | G284: Reunión alineación SGI DEV de LZ | H284: =G284 -> Reunión alineación SGI DEV de LZ | I284: FINALIZADO | J284: 1 | M284: =SUM(J284:J288) -> 8
B285: 46101 | C285: 09:00 - 18:00 | D285: INGENIERIA | E285: Jesús Chávez | F285: REQ | G285: Reunión de Presentación APS de VZOR | H285: =G285 -> Reunión de Presentación APS de VZOR | I285: FINALIZADO | J285: 1
...

Sheet AmericoSaravia
B1: FECHA SOLICITUD | C1: Periodo | D1: AREA / PERSONAL SOLICITANTE | E1: PROFESIONAL | F1: INC / REQ / WARNING | G1: Actividad | H1: Detalle / Observación | I1: Estado (en proceso, pendiente, finalizado) | J1: Tiempo estimado actividad | K1: Ticket
B2: 45719 | C2: 09:00 - 18:59 | D2: Melinka Chacon | E2: Asaravia | F2: REQ | G2: Revisión SGI. Se encontro que problemas venia desde informix. Por lo cual se escalo a Jose Luis | I2: FINALIZADO | J2: 30 min
B3: 45720 | C3: 09:00 - 18:59 | D3: Gonzalo Sepulveda | E3: Gonzalo Sepulveda | F3: REQ | G3: Revisión de configuraciones SSL | I3: FINALIZADO
B4: 45720 | C4: 18:00 - 21:00 | D4: Gonzalo Sepulveda | E4: Gonzalo Sepulveda | F4: REQ | G4: Revisión y pruebas SSL UAT-SIT-DEV | I4: FINALIZADO
B5: 45720 | C5: 09:00 - 18:59 | D5: Jorge Leon | E5: Jorge Leon | F5: REQ | G5: Revisión ODI por proceso pegado, se revisa plataforma encontrando errores de java.lang.OutOfMemoryError, por lo cual se realiza tunning JVM | I5: FINALIZADO
B6: 45720 | C6: 09:00 - 18:59 | D6: Nicolas Patricio Reyes Escalona | E6: Nicolas Patricio Reyes Escalona | F6: REQ | G6: Revisión sistemas de SGI | I6: FINALIZADO
B7: 45722 | C7: 09:00 - 18:59 | D7: Fernanda Yañez | E7: Fernanda Yañez | F7: REQ | G7: revisióbn caida calculo PFP, se realiza reinicio de servicios owsm server | I7: FINALIZADO | K7: ticket # 886 - Sistema PFP Caído // 1440
B8: 45722 | C8: 09:00 - 18:59 | D8: Paola Lillo | E8: Paola Lillo | F8: REQ | G8: Revisión pueto 9001 de server proosb, se realiza reinicio de servicios de osb. | I8: FINALIZADO
B9: 45722 | C9: 09:00 - 18:59 | D9: Jesus Antonio Chavez Bastias | E9: Jesus Antonio Chavez Bastias | F9: REQ | G9: Webservices Alertados - OSBPROD01 | I9: FINALIZADO
B10: 45722 | C10: 09:00 - 18:59 | D10: Jorge Leon | E10: Jorge Leon | F10: REQ | G10: Solicitud revisión de conexiones ODI | I10: FINALIZADO
B11: 45726 | C11: 09:00 - 18:59 | D11: Gema Molina | E11: Gema Molina | F11: REQ | G11: Prueba de conectividad a nivel nacional Teams | I11: FINALIZADO
B12: 45727 | C12: 09:00 - 18:59 | D12: Carlos Salamaca | E12: Carlos Salamaca | F12: REQ | G12: Status Paso a operaciones Portal de Pago | I12: FINALIZADO
B13: 45728 | C13: 09:00 - 18:59 | D13: Paola Lillo | E13: Paola Lillo | F13: REQ | G13: Revisión servidores de QA | I13: FINALIZADO
B14: 45729 | C14: 09:00 - 18:59 | D14: Cristian Villanueva | E14: Cristian Villanueva | F14: REQ | G14: Refvisión ODI y Sistema AF | I14: FINALIZADO
B15: 45729 | C15: 09:00 - 18:59 | D15: Jorge Leon | E15: Jorge Leon | F15: REQ | G15: Solicitud creación ODISYN_ODI_REPO | I15: FINALIZADO
B16: 45730 | C16: 09:00 - 18:59 | D16: Fernanda Yañez | E16: Fernanda Yañez | F16: REQ | G16: Estimados, nos reportan nuevamente que sistema PFP no responde. http://sistemacalculopfp.ips.gob.cl:9001/PFP/login.xhtml | I16: FINALIZADO | K16: ticket # 1444 - Sistema PFP Caído
B17: 45733 | C17: 09:00 - 18:59 | D17: Mauricio Miranda | E17: Mauricio Miranda | F17: REQ | G17: Revisión espacios /u01 de server proosb02, Alertas! Sensor Disk Free: /u01 MV proosb02 IP 10.150.150.104 | I17: FINALIZADO
B18: 45368 | C18: 09:00 - 18:59 | D18: Patricio Ramirez | E18: Patricio Ramirez | F18: REQ | G18: FW: IPS: Revisión caso 3-39559650149 Problemas con OHS después de configurar SSL | I18: FINALIZADO
B19: 45370 | C19: 09:00 - 18:59 | D19: Patricio Ramirez | E19: Patricio Ramirez | F19: REQ | G19: Status Paso a operaciones Portal de Pago. | I19: FINALIZADO
B20: 45370 | C20: 09:00 - 18:59 | D20: Jesuis Chavex | E20: Jesuis Chavex | F20: REQ | G20: Revisar proosb01 no tiene corriendo los procesos httpd.worker? | I20: FINALIZADO
B21: 45737 | C21: 09:00 - 18:59 | D21: Jonathan Nñez | E21: Jonathan Nñez | F21: REQ | G21: Alerta puertos VM Proosb01 (10.150.150.103) PM 20-03 puertos 9001 | I21: FINALIZADO
B22: 45737 | C22: 09:00 - 18:59 | D22: Fernanda Yañez | E22: Fernanda Yañez | F22: REQ | G22: Estimados, nos reportan nuevamente que sistema PFP no responde. http://sistemacalculopfp.ips.gob.cl:9001/PFP/login.xhtml | I22: FINALIZADO | K22: ticket # 1450 - Sistema PFP Caído
B23: 45737 | C23: 09:00 - 18:59 | D23: Patricio Ramirez | E23: Patricio Ramirez | F23: REQ | G23: Status SR 3-39559650149 oracle - SSL - Weblogic | I23: FINALIZADO
B24: 45738 | C24: 09:00 - 18:59 | D24: Patricio Ramirez | E24: Patricio Ramirez | F24: REQ | G24: Se comparten evidencias del caso de SSL oracle | I24: FINALIZADO
B25: 45741 | C25: 09:00 - 18:59 | D25: Williams Franco | E25: Williams Franco | F25: REQ | G25: Estimados, nos reportan nuevamente que sistema PFP no responde. http://sistemacalculopfp.ips.gob.cl:9001/PFP/login.xhtml | I25: FINALIZADO | K25: ticket # 1454 - Sistema PFP Caído
B26: 45741 | C26: 09:00 - 18:59 | D26: Pablo Gallegos | E26: Pablo Gallegos | F26: REQ | G26: Alerta de puerto 9001 dispositivo proosb01 (10.150.150.103) | I26: FINALIZADO
B27: 45741 | C27: 09:00 - 18:59 | D27: Gonzalo Sepulveda | E27: Gonzalo Sepulveda | F27: REQ | G27: Solicitud ejecución plan de cargas | I27: FINALIZADO
B28: 45741 | C28: 18:00 - 21:00 | D28: Gonzalo Sepulveda | E28: Gonzalo Sepulveda | F28: REQ | G28: Reunió soporte Oracle. | I28: FINALIZADO
B29: 45742 | C29: 09:00 - 18:59 | D29: Patricio Ordenes | E29: Patricio Ordenes | F29: REQ | G29: Solicitud de registros log de aplicación SGI - ASIMU | I29: FINALIZADO
B30: 45742 | C30: 09:00 - 18:59 | D30: Christopher Astorga | E30: Christopher Astorga | F30: REQ | G30: [EXTERNO]Alerta de puerto 9001 dispositivo proosb01 (10.150.150.103) | I30: FINALIZADO
B31: 45742 | C31: 09:00 - 18:59 | D31: Williams Franco | E31: Williams Franco | F31: REQ | G31: Estimados, nos reportan nuevamente que sistema PFP no responde. http://sistemacalculopfp.ips.gob.cl:9001/PFP/login.xhtml | I31: FINALIZADO | K31: ticket # 1455 - Sistema PFP Caído
B32: 45742 | C32: 09:00 - 18:59 | D32: Paticio Ordenes | E32: Paticio Ordenes | F32: REQ | G32: Solicitud de lkigs Asimu-geston-interna | I32: FINALIZADO
B33: 46108 | C33: 09:00 - 18:59 | D33: Patricio Ordenes | E33: Patricio Ordenes | F33: REQ | G33: Solicitud revision servicios SGI, se le informa problemas de comunicación de aws | I33: FINALIZADO
B34: 46108 | C34: 09:00 - 18:59 | D34: Patricio Ordenes | E34: Patricio Ordenes | F34: REQ | G34: Reinicio de servicios post recuperación de comunicación aws. | I34: FINALIZADO
B35: 45743 | C35: 09:00 - 18:59 | D35: Daniel Francisco Zamora Galindo | E35: Daniel Francisco Zamora Galindo | F35: REQ | G35: Revisión conexión timed out del server de qa, problemas de comunicación VMC | I35: FINALIZADO
B36: 45747 | C36: 09:00 - 18:59 | D36: Victor Caroca | E36: Victor Caroca | F36: REQ | G36: Solicitu revisión sistemas de CHA se le informa prioclemas de comunicaciones | I36: FINALIZADO
B37: 45748 | C37: 09:00 - 18:00 | D37: Fernanda Yañez | E37: Asaravia | F37: REQ | G37: revisióbn caida calculo PFP, se realiza reinicio de servicios owsm server | I37: FINALIZADO | K37: IM-209827-4-1459
B38: 45749 | C38: 09:00 - 18:00 | D38: Fernanda Yañez | E38: Asaravia | F38: REQ | G38: revisióbn caida calculo PFP, se realiza reinicio de servicios owsm server | I38: FINALIZADO | K38: IM-209965-4-1460
B39: 45751 | C39: 09:00 - 18:59 | D39: Melinka Chacon | E39: Asaravia | F39: REQ | G39: Reporta problemas en SGI, esto fue por un parchado de seguridad aplicado por infra a solicitud de seguridad, (PrimeFace) | I39: FINALIZADO
B40: 45754 | C40: 09:00 - 18:59 | D40: Jesus Chavez | E40: Asaravia | F40: REQ | G40: Informa alerta en server wls03 se encuentra con los puertos abajo. Se le informa que se esta trabajando para volver atrás un parchado | I40: FINALIZADO
B41: 45751 | C41: 09:00 - 18:59 | D41: Patricio Gabriel | E41: Asaravia | F41: REQ | G41: Reunión de por incidente wla03-04 por un parchado de seguridad aplicado por infra a solicitud de seguridad, (PrimeFace) | I41: FINALIZADO
B42: 45754 | C42: 09:00 - 18:59 | D42: Jonathan Alexander Nunez Aranguiz | E42: Asaravia | F42: REQ | G42: Junto con desearles , les comento que se encuentran las siguientes alertas de puerto dispositivo proosb01 (10.150.150.103) puerto 9001 | I42: FINALIZADO
B43: 45754 | C43: 09:00 - 18:59 | D43: Jesus Chavez | E43: Asaravia | F43: REQ | G43: Informa alerta en server wls04, se le informa que hubo parchado de seguridad el cual dejo un incidente en wls03 y wls04 | I43: FINALIZADO
B44: 45754 | C44: 09:00 - 18:59 | D44: Victor Venegas | E44: Asaravia | F44: REQ | G44: Junto con desearles , les comento que se encuentran las siguientes alertas de puerto dispositivo proosb02 (10.150.150.104) puerto 9002 | I44: FINALIZADO
B45: 45754 | C45: 09:00 - 18:59 | D45: Jose Luis Hernandez | E45: Asaravia | F45: REQ | G45: Vuelta atrás parchado de maquina wls'3 por parte de infra | I45: FINALIZADO
B46: 45755 | C46: 09:00 - 18:59 | D46: Gonzalo Sepulveda | E46: Asaravia | F46: REQ | G46: Inicio Plan de carga UAT solicitado por Gonzalo | I46: FINALIZADO | K46: 14536 / RF-210310-4-14536
B47: 45755 | C47: 09:00 - 18:59 | D47: Christian Segura | E47: Asaravia | F47: REQ | G47: Se solicita a Christian probar funcionamiento de SGI | I47: FINALIZADO
B48: 45756 | C48: 09:00 - 18:59 | D48: Jorge Leon | E48: Asaravia | F48: REQ | G48: Reporta problemas con ODI de datos. Se reinicia el agente. | I48: FINALIZADO
B49: 45757 | C49: 09:00 - 18:59 | D49: Jesus Chavez | E49: Asaravia | F49: REQ | G49: se informa a Jesus chavez que fue restablecido servicio de wls03 | I49: FINALIZADO
B50: 45758 | C50: 09:00 - 18:59 | D50: Christian Segura | E50: Asaravia | F50: REQ | G50: Christian consulta por estado de configuración SSL en ambientes de PDP | I50: FINALIZADO
B51: 45761 | C51: 09:00 - 18:59 | D51: Paola | E51: Asaravia | F51: REQ | G51: Paola reporta puerto debajo de proosb. Se le informa que servicios estan ok, de todos modos se reinicia. | I51: FINALIZADO
B52: 45762 | C52: 09:00 - 18:59 | D52: Patricio Ramirez | E52: Asaravia | F52: REQ | G52: reunión revisión entrega de pdp | I52: FINALIZADO
B53: 45762 | C53: 09:00 - 18:59 | D53: Patricio Ramirez | E53: Asaravia | F53: REQ | G53: Informe de incidente PFP causa raiz de caidas. | I53: FINALIZADO
B54: 45762 | C54: 09:00 - 18:59 | D54: Patricio Ordenes | E54: Asaravia | F54: REQ | G54: Por favor, su ayuda para revisar el servidor http://10.150.226.96:7001/console que está presentando problemas | I54: FINALIZADO | K54: Caso No. 14625 / RF-210834-4-14625
B55: 45762 | C55: 09:00 - 18:59 | D55: Fernanda Yañez | E55: Asaravia | F55: REQ | G55: Reicicio servicios PFP | I55: FINALIZADO
B56: 45762 | C56: 09:00 - 18:59 | D56: Jose Cruces | E56: Asaravia | F56: REQ | G56: Solicitud de revisión Causa raiz caidas PFP | I56: FINALIZADO
B57: 45762 | C57: 09:00 - 18:59 | D57: Jose Luis Hernandez | E57: Asaravia | F57: REQ | G57: consulta si se tiene la causa raiz de caidas PFP con personal de CHA | I57: FINALIZADO
B58: 45762 | C58: 09:00 - 18:59 | D58: Jose Luis Hernandez | E58: Asaravia | F58: REQ | G58: Reunión caidas PFP con personal de CHA | I58: FINALIZADO
B59: 45762 | C59: 09:00 - 18:59 | D59: Paola Lillo | E59: Asaravia | F59: REQ | G59: Solicitud actualización de diagrama IPS en linea y AFPEr | I59: FINALIZADO
B60: 45763 | C60: 09:00 - 18:59 | D60: Gonzalo Sepulveda | E60: Asaravia | F60: REQ | G60: favor hacerme llegar el siguiente archivo feriados.properties | I60: FINALIZADO | K60: Caso No. 14631 / RF-210870-4-14631
B61: 45763 | C61: 09:00 - 18:59 | D61: Jose Luis Hernaandez | E61: Asaravia | F61: REQ | G61: Reinicios de servicios owsm por falla en BD de informix | I61: FINALIZADO
B62: 45763 | C62: 09:00 - 18:59 | D62: Patricio Ramirez | E62: Asaravia | F62: REQ | G62: Reporta incidente en BD informix | I62: FINALIZADO
B63: 45763 | C63: 09:00 - 18:59 | D63: Gonzalo Sepulveda | E63: Asaravia | F63: REQ | G63: Configuración virtua host en ssl.conf de SIT para pdp. | I63: FINALIZADO
B64: 45764 | C64: 09:00 - 18:59 | D64: Maria Fatima Requena Canepa | E64: Asaravia | F64: REQ | G64: Reicicio servicios PFP | I64: FINALIZADO | K64: Caso No. 1479 / IM-210975-4-1479
B65: 45764 | C65: 09:00 - 18:59 | D65: Christian Segura | E65: Asaravia | F65: REQ | G65: Se le informan avances de configuración SSL en SIT | I65: FINALIZADO
B66: 45764 | C66: 09:00 - 18:59 | D66: Patricio Ramirez | E66: Asaravia | F66: REQ | G66: Se envia correo de información pruebas ssl | I66: FINALIZADO
B67: 45763 | C67: 09:00 - 18:59 | D67: Gonzalo Sepulveda | E67: Asaravia | F67: REQ | G67: Pruebas de ssl en ambiente SIT con gonzalo y desarrollo. | I67: FINALIZADO
B68: 45765 | C68: 09:00 - 18:59 | D68: Gonzalo Sepulveda | E68: Asaravia | F68: REQ | G68: Configuración SSL PDP DEV | I68: FINALIZADO
B69: 45768 | C69: 09:00 - 18:59 | D69: Cristian Salazar | E69: Asaravia | F69: REQ | G69: Reinicio de sevicios PFP | I69: FINALIZADO
B70: 45769 | C70: 09:00 - 18:59 | D70: Victor Caroca | E70: Asaravia | F70: REQ | G70: Solicitud revisión servicios OSB de QA | I70: FINALIZADO
B71: 45769 | C71: 09:00 - 18:59 | D71: Claudia Flores | E71: Asaravia | F71: REQ | G71: Revisión de servicio PFP, reportan servicio intermitente. | I71: FINALIZADO
B72: 45770 | C72: 09:00 - 18:59 | D72: Patricio Ordenes | E72: Asaravia | F72: REQ | G72: Revisión de congiguración osb de afper uat http://afper-uat-osb.ips.gob.cl:7003/AFPProject/ConsultaSIAGF | I72: FINALIZADO
B73: 45770 | C73: 09:00 - 18:59 | D73: Patricio Ordenes | E73: Asaravia | F73: REQ | G73: Revisión de congiguración osb de afper PRD http://afper-prd-osb.ips.gob.cl:7003/AFPProject/ConsultaSIAGF | I73: FINALIZADO
B74: 45770 | C74: 09:00 - 18:59 | D74: Paola Lillo | E74: Asaravia | F74: REQ | G74: Diseño y entrega de diagrama de ips en linea | I74: FINALIZADO
B75: 45770 | C75: 09:00 - 18:59 | D75: Gonzalo Sepulveda | E75: Asaravia | F75: REQ | G75: Solicita ayuda para poder restaurar problema en wlcdev por levantar servicios con root | I75: FINALIZADO
B76: 45771 | C76: 09:00 - 18:59 | D76: Gonzalo Sepulveda | E76: Asaravia | F76: REQ | G76: Inicio Plan de carga UAT solicitado por Gonzalo | I76: FINALIZADO | K76: Caso No. 14711 / RF-211342-4-14711
B77: 45771 | C77: 09:00 - 18:59 | D77: Patricio Salinas Olave | E77: Asaravia | F77: REQ | G77: Configuración de OSB solicitud de xml de configuraciones | I77: FINALIZADO
B78: 45771 | C78: 09:00 - 18:59 | D78: Patricio Salinas Olave | E78: Asaravia | F78: REQ | G78: Se les informan problemas de BD para levantar los servicios de OSB | I78: FINALIZADO
B79: 45771 | C79: 09:00 - 18:59 | D79: Sergio Santibañez | E79: Asaravia | F79: REQ | G79: Sergio inforema que el llega a consumir los wsdl del osb, se le comenta que el problema reportado por BD esta relacionado al funcionamiento de la consola | I79: FINALIZADO
B80: 45772 | C80: 09:00 - 18:59 | D80: Paola Lillo | E80: Asaravia | F80: REQ | G80: Reporta problemas de espacio en servidor PRD-Afper-Consulta-17 (10.200.17.252) , se eliminan logs obsoletos para regularizar espacios. | I80: FINALIZADO
B81: 45805 | C81: 09:00 - 18:59 | D81: Gabriel Ramirez | E81: Asaravia | F81: REQ | G81: Solicita que le compartan manual de purga de logs en ODI PDP | I81: FINALIZADO
B82: 45777 | C82: 09:00 - 18:59 | D82: Jose Rodrigo Cruces Aguilera | E82: Asaravia | F82: REQ | G82: reunión Analisis CAidas Calculo PFP | I82: FINALIZADO
B83: 45777 | C83: 09:00 - 18:59 | D83: Oscar Alex Conejeros Muñoz | E83: Asaravia | F83: REQ | G83: Solicitud de revisión de calculo PFP | I83: FINALIZADO
B84: 45779 | C84: 08:00 - 18:00 | D84: Gonzalo Sepulveda | E84: Asaravia | F84: REQ | G84: Revisión de portal de pagos web ambiente sit | I84: FINALIZADO
B85: 45782 | C85: 08:00 - 18:00 | D85: Gonzalo Sepulveda | E85: Asaravia | F85: REQ | G85: Revisión de portal de pagos web ambiente sit por implementación https | I85: FINALIZADO
B86: 45782 | C86: 08:00 - 18:00 | D86: Gonzalo Sepulveda | E86: Asaravia | F86: REQ | G86: Reiniciar ambiente prd de PDP | I86: FINALIZADO
B87: 45782 | C87: 08:00 - 18:00 | D87: Gonzalo Sepulveda | E87: Asaravia | F87: REQ | G87: Ejecutar plan de carga ambiente prd de PDP | I87: FINALIZADO
B88: 45782 | C88: 08:00 - 18:00 | D88: Jesus Chavez | E88: Asaravia | F88: REQ | G88: Revisión APM PFP | I88: FINALIZADO
... B156: 45831 | C156: 08:00 - 18:00 | D156: Victor Caroca | E156: Asaravia | F156: REQ | G156: consultarte un tema con el ambiente desarrolo, que necesitamos forzar que utilize el tls 1.1 pero eso se configura al momento de iniciar. | I156: FINALIZADO
G157: Se le informa que debe consultar a seguridad, ya que los servicios estan con TLS1.2 | I157: FINALIZADO
B158: 45832 | C158: 08:00 - 18:00 | D158: Victor Caroca | E158: Asaravia | F158: REQ | G158: Consulta por servicios de osbqa | I158: FINALIZADO
B159: 45833 | C159: 08:00 - 18:00 | D159: Patricio Odenes | E159: Asaravia | F159: REQ | G159: Solicitud revisión de servicios http://osbprod01.ips.gob.cl:8001/BEN_Asimu/EXP/PS/PX_EXP_Asimu_gestionaSolicitud?wsdl | I159: FINALIZADO
B160: 45834 | C160: 08:00 - 18:00 | D160: Patricio Odenes | E160: Asaravia | F160: REQ | G160: solicitud de revisión servicios osbpro01. | I160: FINALIZADO
B161: 45834 | C161: 08:00 - 18:00 | D161: Patricio Odenes | E161: Asaravia | F161: REQ | G161: Revisión servicio principal de la elegibilidad del ASIMU | I161: FINALIZADO
B162: 45838 | C162: 08:00 - 18:00 | D162: Paola Lillo | E162: Asaravia | F162: REQ | G162: Informa espacio del server 10.150.226.96 | I162: FINALIZADO
B163: 45838 | C163: 08:00 - 18:00 | D163: Jorge Echeñique | E163: Asaravia | G163: reporta problemas en servicio Historico Previsional, se le informa que responde desde el osb, deben revisar firewall | I163: FINALIZADO
B164: 45840 | C164: 08:00 - 18:00 | D164: Jorge Echeñique | E164: Asaravia | F164: REQ | G164: reporta problemas en servicio Historico Previsional, se le informa que responde desde el osb, deben revisar firewall | I164: FINALIZADO
B165: 45840 | C165: 08:00 - 18:00 | D165: Paola Lillo | E165: Asaravia | F165: REQ | G165: Revisión Filesystem weblogicQA (10.150.226.95) weblogicBPMQA (10.150.226.212) | I165: FINALIZADO
B166: 45841 | C166: 08:00 - 18:00 | D166: Patricio Odenes | E166: Asaravia | F166: REQ | G166: solicitud de logs cm_asimu_gestion-interna | I166: FINALIZADO
B167: 45841 | C167: 08:00 - 18:00 | D167: Patricio Odenes | E167: Asaravia | F167: REQ | G167: Reunión incidencia Asimu, problemas pára guardar registro, se revisa plataforma sin problemas | I167: FINALIZADO
...

Sheet JPBuzeta
B1: FECHA SOLICITUD | C1: Periodo | D1: AREA / PERSONAL SOLICITANTE | E1: PROFESIONAL | F1: INC / REQ / WARNING | G1: Actividad | H1: Detalle / Observación | I1: Estado (en proceso, pendiente, finalizado) | J1: Tiempo estimado actividad
B2: 45735 | C2: 45717 | D2: NOC IPS | E2: Juan Pablo Buzeta | F2: REQ | G2: Revision de respados VeeamBackup | H2: Revision del resultado del JOB y tomar acciones si corresponde
B3: 45735 | C3: 45717 | D3: NOC IPS | E3: Juan Pablo Buzeta | F3: REQ | G3: Revision de alertas VZOR | H3: Checheo diario de alertas en herramienta VZOR
B4: 45735 | C4: 45717 | D4: NOC IPS | E4: Juan Pablo Buzeta | F4: REQ | G4: Revision de Plugins VZOR | H4: Ajuste de umbrales y monitoreos / escalamientos con VZOR
B5: 45735 | C5: 45717 | D5: NOC IPS | E5: Juan Pablo Buzeta | F5: REQ | G5: Revision de servidores | H5: Configuracion y ajustes de monitoreo
B6: 45736 | C6: 45717 | D6: NOC IPS | E6: Juan Pablo Buzeta | F6: REQ | G6: Revision de respados VeeamBackup | H6: Revision del resultado del JOB y tomar acciones si corresponde
B7: 45736 | C7: 45717 | D7: NOC IPS | E7: Juan Pablo Buzeta | F7: REQ | G7: Revision de alertas VZOR | H7: Checheo diario de alertas en herramienta VZOR
B8: 45736 | C8: 45717 | D8: NOC IPS | E8: Juan Pablo Buzeta | F8: REQ | G8: Revision de Plugins VZOR | H8: Ajuste de umbrales y monitoreos / escalamientos con VZOR
B9: 45736 | C9: 45717 | D9: NOC IPS | E9: Juan Pablo Buzeta | F9: REQ | G9: Revision de servidores | H9: Configuracion y ajustes de monitoreo
B10: 45737 | C10: 45717 | D10: NOC IPS | E10: Juan Pablo Buzeta | F10: REQ | G10: Revision de respados VeeamBackup | H10: Revision del resultado del JOB y tomar acciones si corresponde
B11: 45737 | C11: 45717 | D11: NOC IPS | E11: Juan Pablo Buzeta | F11: REQ | G11: Revision de alertas VZOR | H11: Checheo diario de alertas en herramienta VZOR
B12: 45737 | C12: 45717 | D12: NOC IPS | E12: Juan Pablo Buzeta | F12: REQ | G12: Revision de Plugins VZOR | H12: Ajuste de umbrales y monitoreos / escalamientos con VZOR
B13: 45737 | C13: 45717 | D13: NOC IPS | E13: Juan Pablo Buzeta | F13: REQ | G13: Revision de servidores | H13: Configuracion y ajustes de monitoreo
... B971: 46058 | C971: 46054 | D971: NOC IPS | E971: Juan Pablo Buzeta | F971: INC | G971: Alerta con la conexión en el server Prod_ODI02 - IP 10.150.150.109 | H971: alerta con la desconexión desde Vzor del server Prod_ODI02 - IP 10.150.150.109
B972: 46058 | C972: 46054 | D972: NOC IPS | E972: Juan Pablo Buzeta | G972: Alerta server bdfmwaws - FMW/FMW - IP 10.150.216.23 | H972: alerta con la desconexion en el server bdfmwaws - FMW/FMW - IP 10.150.216.23
B973: 46058 | C973: 46054 | D973: NOC IPS | E973: Juan Pablo Buzeta | G973: Alerta con los server de BD ﻿dbesitpp01 - PRYSIT - IP 10.150.234.95 y ﻿dbesitpp01 - PPSIT - IP 10.150.234.95 | H973: Alerta después de la restauración masiva en VZOR con los siguientes server: BD ﻿dbesitpp01 - PRYSIT - IP 10.150.234.95 dbesitpp01 - PPSIT - IP 10.150.234.95 CRITICAL - cannot connect to (DESCRIPTION=(ADDRESS=(PROTOCOL=TCP)(HOST=10.150.234.95)(PORT=1521))(CONNECT_DATA=(SID=PRYSIT))). timeout alarm
B974: 46059 | C974: 46054 | D974: NOC IPS | E974: Juan Pablo Buzeta | F974: REQ | G974: Revision de veeam BKP | H974: Configuracion y ajustes de respaldos
B975: 46059 | C975: 46054 | D975: NOC IPS | E975: Juan Pablo Buzeta | F975: REQ | G975: Revision de alertas VZOR | H975: Checheo diario de alertas en herramienta VZOR
B976: 46059 | C976: 46054 | D976: NOC IPS | E976: Juan Pablo Buzeta | F976: REQ | G976: Revision de Plugins VZOR | H976: Ajuste de umbrales y monitoreos / escalamientos con VZOR
B977: 46059 | C977: 46054 | D977: NOC IPS | E977: Juan Pablo Buzeta | F977: REQ | G977: Revision de servidores | H977: Configuracion y ajustes de monitoreo
B978: 46062 | C978: 46054 | D978: NOC IPS | E978: Juan Pablo Buzeta | F978: REQ | G978: Revision de Monitoreos Desconocidos y Criticos | H978: Revision de Monitoreos Desconocidos y Criticos
B979: 46062 | C979: 46054 | D979: NOC IPS | E979: Juan Pablo Buzeta | F979: REQ | G979: Revision de veeam BKP | H979: Configuracion y ajustes de respaldos
B980: 46062 | C980: 46054 | D980: NOC IPS | E980: Juan Pablo Buzeta | F980: REQ | G980: Revision de alertas VZOR | H980: Checheo diario de alertas en herramienta VZOR
B981: 46062 | C981: 46054 | D981: NOC IPS | E981: Juan Pablo Buzeta | F981: REQ | G981: Revision de Plugins VZOR | H981: Ajuste de umbrales y monitoreos / escalamientos con VZOR
B982: 46062 | C982: 46054 | D982: NOC IPS | E982: Juan Pablo Buzeta | F982: REQ | G982: Revision de servidores | H982: Configuracion y ajustes de monitoreo
B983: 46063 | C983: 46054 | D983: NOC IPS | E983: Juan Pablo Buzeta | F983: REQ | G983: Revision de Monitoreos Desconocidos y Criticos | H983: Revision de Monitoreos Desconocidos y Criticos
B984: 46063 | C984: 46054 | D984: NOC IPS | E984: Juan Pablo Buzeta | F984: REQ | G984: Revision de veeam BKP | H984: Configuracion y ajustes de respaldos
B985: 46063 | C985: 46054 | D985: NOC IPS | E985: Juan Pablo Buzeta | F985: REQ | G985: Revision de alertas VZOR | H985: Checheo diario de alertas en herramienta VZOR
... B1098: 46091 | C1098: 46082 | D1098: NOC IPS | E1098: Juan Pablo Buzeta | F1098: REQ | G1098: Revision de servidores | H1098: Configuracion y ajustes de monitoreo
B1099: 46092 | C1099: 46082 | D1099: NOC IPS | E1099: Juan Pablo Buzeta | F1099: REQ | G1099: Revision de Monitoreos Desconocidos y Criticos | H1099: Revision de Monitoreos Desconocidos y Criticos | I1099: Finalizado | J1099: 2
B1100: 46092 | C1100: 46082 | D1100: NOC IPS | E1100: Juan Pablo Buzeta | F1100: REQ | G1100: Revision de veeam BKP | H1100: Configuracion y ajustes de respaldos | I1100: Finalizado | J1100: 1
B1101: 46092 | C1101: 46082 | D1101: NOC IPS | E1101: Juan Pablo Buzeta | F1101: REQ | G1101: Revision de alertas VZOR | H1101: Checheo diario de alertas en herramienta VZOR | I1101: Finalizado | J1101: 4
B1102: 46092 | C1102: 46082 | D1102: NOC IPS | E1102: Juan Pablo Buzeta | F1102: REQ | G1102: Revision de Plugins VZOR | H1102: Ajuste de umbrales y monitoreos / escalamientos con VZOR | I1102: Finalizado | J1102: 1
B1103: 46092 | C1103: 46082 | D1103: NOC IPS | E1103: Juan Pablo Buzeta | F1103: REQ | G1103: Revision de servidores | H1103: Configuracion y ajustes de monitoreo | I1103: Finalizado | J1103: 1
B1104: 46093 | C1104: 46082 | D1104: NOC IPS | E1104: Juan Pablo Buzeta | F1104: REQ | G1104: Revision de Monitoreos Desconocidos y Criticos | H1104: Revision de Monitoreos Desconocidos y Criticos | I1104: Finalizado | J1104: 2
B1105: 46093 | C1105: 46082 | D1105: NOC IPS | E1105: Juan Pablo Buzeta | F1105: REQ | G1105: Revision de veeam BKP | H1105: Configuracion y ajustes de respaldos | I1105: Finalizado | J1105: 1
B1106: 46093 | C1106: 46082 | D1106: NOC IPS | E1106: Juan Pablo Buzeta | F1106: REQ | G1106: Revision de alertas VZOR | H1106: Checheo diario de alertas en herramienta VZOR | I1106: Finalizado | J1106: 4
B1107: 46093 | C1107: 46082 | D1107: NOC IPS | E1107: Juan Pablo Buzeta | F1107: REQ | G1107: Revision de Plugins VZOR | H1107: Ajuste de umbrales y monitoreos / escalamientos con VZOR | I1107: Finalizado | J1107: 1
B1108: 46093 | C1108: 46082 | D1108: NOC IPS | E1108: Juan Pablo Buzeta | F1108: REQ | G1108: Revision de servidores | H1108: Configuracion y ajustes de monitoreo | I1108: Finalizado | J1108: 1
B1109: 46094 | C1109: 46082 | D1109: NOC IPS | E1109: Juan Pablo Buzeta | F1109: REQ | G1109: Revision de Monitoreos Desconocidos y Criticos | H1109: Revision de Monitoreos Desconocidos y Criticos | I1109: Finalizado | J1109: 2
B1110: 46094 | C1110: 46082 | D1110: NOC IPS | E1110: Juan Pablo Buzeta | F1110: REQ | G1110: Revision de veeam BKP | H1110: Configuracion y ajustes de respaldos | I1110: Finalizado | J1110: 1
... B1175: 46108 | C1175: 46082 | D1175: NOC IPS | E1175: Juan Pablo Buzeta | F1175: REQ | G1175: Auditoría de cobertura de monitoreo | H1175: Identificación de servicios sin monitoreo, brechas de cobertura y configuraciones incompletas en la plataforma. | I1175: Finalizado | J1175: 1

Sheet CarlosJara
B1: FECHA SOLICITUD | C1: Periodo | D1: AREA / PERSONAL SOLICITANTE | E1: PROFESIONAL | F1: INC / REQ / WARNING | G1: Actividad | H1: Detalle / Observación | I1: Estado (en proceso, pendiente, finalizado) | J1: Tiempo estimado actividad
B2: 45735 | C2: 45717 | D2: NOC IPS | E2: Carlos Jara | F2: REQ | G2: Revision de respados VeeamBackup | H2: Revision del resultado del JOB y tomar acciones si corresponde
B3: 45735 | C3: 45717 | D3: NOC IPS | E3: Carlos Jara | F3: REQ | G3: Revision de alertas VZOR | H3: Checheo diario de alertas en herramienta VZOR
B4: 45735 | C4: 45717 | D4: NOC IPS | E4: Carlos Jara | F4: REQ | G4: Revision de Plugins VZOR | H4: Ajuste de umbrales y monitoreos / escalamientos con VZOR
B5: 45735 | C5: 45717 | D5: NOC IPS | E5: Carlos Jara | F5: REQ | G5: Revision de servidores | H5: Configuracion y ajustes de monitoreo
B6: 45736 | C6: 45717 | D6: NOC IPS | E6: Carlos Jara | F6: REQ | G6: Revision de respados VeeamBackup | H6: Revision del resultado del JOB y tomar acciones si corresponde
B7: 45736 | C7: 45717 | D7: NOC IPS | E7: Carlos Jara | F7: REQ | G7: Revision de alertas VZOR | H7: Checheo diario de alertas en herramienta VZOR
B8: 45736 | C8: 45717 | D8: NOC IPS | E8: Carlos Jara | F8: REQ | G8: Revision de Plugins VZOR | H8: Ajuste de umbrales y monitoreos / escalamientos con VZOR
B9: 45736 | C9: 45717 | D9: NOC IPS | E9: Carlos Jara | F9: REQ | G9: Revision de servidores | H9: Configuracion y ajustes de monitoreo
B10: 45737 | C10: 45717 | D10: NOC IPS | E10: Carlos Jara | F10: REQ | G10: Revision de respados VeeamBackup | H10: Revision del resultado del JOB y tomar acciones si corresponde
B11: 45737 | C11: 45717 | D11: NOC IPS | E11: Carlos Jara | F11: REQ | G11: Revision de alertas VZOR | H11: Checheo diario de alertas en herramienta VZOR
B12: 45737 | C12: 45717 | D12: NOC IPS | E12: Carlos Jara | F12: REQ | G12: Revision de Plugins VZOR | H12: Ajuste de umbrales y monitoreos / escalamientos con VZOR
B13: 45737 | C13: 45717 | D13: NOC IPS | E13: Carlos Jara | F13: REQ | G13: Revision de servidores | H13: Configuracion y ajustes de monitoreo
... B1022: 46052 | C1022: 46023 | D1022: NOC IPS | E1022: Carlos Jara | F1022: REQ | G1022: Revision de servidores | H1022: Configuracion y ajustes de monitoreo
B1023: 46055 | C1023: 46054 | D1023: NOC IPS | E1023: Carlos Jara | G1023: Vacaciones | H1023: Vacaciones
B1024: 46056 | C1024: 46054 | D1024: NOC IPS | E1024: Carlos Jara | G1024: Vacaciones | H1024: Vacaciones
B1025: 46057 | C1025: 46054 | D1025: NOC IPS | E1025: Carlos Jara | G1025: Vacaciones | H1025: Vacaciones
B1026: 46058 | C1026: 46054 | D1026: NOC IPS | E1026: Carlos Jara | G1026: Vacaciones | H1026: Vacaciones
B1027: 46059 | C1027: 46054 | D1027: NOC IPS | E1027: Carlos Jara | G1027: Vacaciones | H1027: Vacaciones
B1028: 46062 | C1028: 46054 | D1028: NOC IPS | E1028: Carlos Jara | F1028: REQ | G1028: Revision de Monitoreos Desconocidos y Criticos | H1028: Revision de Monitoreos Desconocidos y Criticos
B1029: 46062 | C1029: 46054 | D1029: NOC IPS | E1029: Carlos Jara | F1029: REQ | G1029: Revision de veeam BKP | H1029: Configuracion y ajustes de respaldos
B1030: 46062 | C1030: 46054 | D1030: NOC IPS | E1030: Carlos Jara | F1030: REQ | G1030: Revision de alertas VZOR | H1030: Checheo diario de alertas en herramienta VZOR
B1031: 46062 | C1031: 46054 | D1031: NOC IPS | E1031: Carlos Jara | F1031: REQ | G1031: Revision de Plugins VZOR | H1031: Ajuste de umbrales y monitoreos / escalamientos con VZOR
B1032: 46062 | C1032: 46054 | D1032: NOC IPS | E1032: Carlos Jara | F1032: REQ | G1032: Revision de servidores | H1032: Configuracion y ajustes de monitoreo
B1033: 46063 | C1033: 46054 | D1033: NOC IPS | E1033: Carlos Jara | F1033: REQ | G1033: Revision de Monitoreos Desconocidos y Criticos | H1033: Revision de Monitoreos Desconocidos y Criticos
B1034: 46063 | C1034: 46054 | D1034: NOC IPS | E1034: Carlos Jara | F1034: REQ | G1034: Revision de veeam BKP | H1034: Configuracion y ajustes de respaldos
B1035: 46063 | C1035: 46054 | D1035: NOC IPS | E1035: Carlos Jara | F1035: REQ | G1035: Revision de alertas VZOR | H1035: Checheo diario de alertas en herramienta VZOR
B1036: 46063 | C1036: 46054 | D1036: NOC IPS | E1036: Carlos Jara | F1036: REQ | G1036: Revision de Plugins VZOR | H1036: Ajuste de umbrales y monitoreos / escalamientos con VZOR
B1037: 46063 | C1037: 46054 | D1037: NOC IPS | E1037: Carlos Jara | F1037: REQ | G1037: Revision de servidores | H1037: Configuracion y ajustes de monitoreo
B1038: 46064 | C1038: 46054 | D1038: NOC IPS | E1038: Carlos Jara | F1038: REQ | G1038: Revision de Monitoreos Desconocidos y Criticos | H1038: Revision de Monitoreos Desconocidos y Criticos
B1039: 46064 | C1039: 46054 | D1039: NOC IPS | E1039: Carlos Jara | F1039: REQ | G1039: Revision de veeam BKP | H1039: Configuracion y ajustes de respaldos
... B1139: 46091 | C1139: 46082 | D1139: NOC IPS | E1139: Carlos Jara | F1139: REQ | G1139: Revision de servidores | H1139: Configuracion y ajustes de monitoreo
B1140: 46092 | C1140: 46082 | D1140: NOC IPS | E1140: Carlos Jara | F1140: REQ | G1140: Revision de Monitoreos Desconocidos y Criticos | H1140: Revision de Monitoreos Desconocidos y Criticos | I1140: Finalizado | J1140: 4
B1141: 46092 | C1141: 46082 | D1141: NOC IPS | E1141: Carlos Jara | F1141: REQ | G1141: Revision de veeam BKP | H1141: Configuracion y ajustes de respaldos | I1141: Finalizado | J1141: 1
B1142: 46092 | C1142: 46082 | D1142: NOC IPS | E1142: Carlos Jara | F1142: REQ | G1142: Revision de alertas VZOR | H1142: Checheo diario de alertas en herramienta VZOR | I1142: Finalizado | J1142: 4
B1143: 46092 | C1143: 46082 | D1143: NOC IPS | E1143: Carlos Jara | F1143: REQ | G1143: Revision de Plugins VZOR | H1143: Ajuste de umbrales y monitoreos / escalamientos con VZOR | I1143: Finalizado | J1143: 2
B1144: 46092 | C1144: 46082 | D1144: NOC IPS | E1144: Carlos Jara | F1144: REQ | G1144: Revision de servidores | H1144: Configuracion y ajustes de monitoreo en App | I1144: Finalizado | J1144: 1
B1145: 46093 | C1145: 46082 | D1145: NOC IPS | E1145: Carlos Jara | F1145: REQ | G1145: Revision de Monitoreos Desconocidos y Criticos | H1145: Revision de Monitoreos Desconocidos y Criticos | I1145: Finalizado | J1145: 4
B1146: 46093 | C1146: 46082 | D1146: NOC IPS | E1146: Carlos Jara | F1146: REQ | G1146: Revision de veeam BKP | H1146: Configuracion y ajustes de respaldos | I1146: Finalizado | J1146: 1
B1147: 46093 | C1147: 46082 | D1147: NOC IPS | E1147: Carlos Jara | F1147: REQ | G1147: Revision de alertas VZOR | H1147: Checheo diario de alertas en herramienta VZOR | I1147: Finalizado | J1147: 4
B1148: 46093 | C1148: 46082 | D1148: NOC IPS | E1148: Carlos Jara | F1148: REQ | G1148: Revision de Plugins VZOR | H1148: Ajuste de umbrales y monitoreos / escalamientos con VZOR | I1148: Finalizado | J1148: 2
B1149: 46093 | C1149: 46082 | D1149: NOC IPS | E1149: Carlos Jara | F1149: REQ | G1149: Revision de servidores | H1149: Configuracion y ajustes de monitoreo en App | I1149: Finalizado | J1149: 1
B1150: 46094 | C1150: 46082 | D1150: NOC IPS | E1150: Carlos Jara | F1150: REQ | G1150: Revision de Monitoreos Desconocidos y Criticos | H1150: Revision de Monitoreos Desconocidos y Criticos | I1150: Finalizado | J1150: 4
B1151: 46094 | C1151: 46082 | D1151: NOC IPS | E1151: Carlos Jara | F1151: REQ | G1151: Revision de veeam BKP | H1151: Configuracion y ajustes de respaldos | I1151: Finalizado | J1151: 1
... B1214: 46111 | C1214: 46082 | D1214: NOC IPS | E1214: Carlos Jara | F1214: REQ | G1214: Auditoría de monitoreo | H1214: Identificación de servicios sin monitoreo o con configuración incompleta | I1214: En Proceso | J1214: 1

Sheet CristiánVásquez
B1: FECHA SOLICITUD | C1: Periodo | D1: AREA / PERSONAL SOLICITANTE | E1: PROFESIONAL | F1: INC / REQ / WARNING | G1: Actividad | H1: Detalle / Observación | I1: Estado (en proceso, pendiente, finalizado) | J1: Tiempo estimado actividad
B2: 45889 | C2: 45870 | D2: NOC IPS | E2: Cristián Vásquez | F2: REQ | G2: Revision de alertas VZOR | H2: Chequeo diario de alertas en herramienta VZOR
B3: 45889 | C3: 45870 | D3: NOC IPS | E3: Cristián Vásquez | F3: REQ | G3: Revision de Plugins VZOR | H3: Ajuste de umbrales y monitoreos / escalamientos con VZOR
B4: 45889 | C4: 45870 | D4: NOC IPS | E4: Cristián Vásquez | F4: REQ | G4: Revision de servidores | H4: Configuración y ajustes de monitoreo
B5: 45890 | C5: 45870 | D5: NOC IPS | E5: Cristián Vásquez | F5: REQ | G5: Revision de respaldos VeeamBackup | H5: Revisión del resultado del JOB y tomar acciones si corresponde
B6: 45890 | C6: 45870 | D6: NOC IPS | E6: Cristián Vásquez | F6: REQ | G6: Revision de alertas VZOR | H6: Chequeo diario de alertas en herramienta VZOR
B7: 45890 | C7: 45870 | D7: NOC IPS | E7: Cristián Vásquez | F7: REQ | G7: Revision de Plugins VZOR | H7: Ajuste de umbrales y monitoreos / escalamientos con VZOR
B8: 45890 | C8: 45870 | D8: NOC IPS | E8: Cristián Vásquez | F8: REQ | G8: Revision de respaldos VeeamBackup | H8: Revisión del resultado del JOB y tomar acciones si corresponde
B9: 45891 | C9: 45870 | D9: NOC IPS | E9: Cristián Vásquez | F9: REQ | G9: Revision de alertas VZOR | H9: Chequeo diario de alertas en herramienta VZOR
B10: 45891 | C10: 45870 | D10: NOC IPS | E10: Cristián Vásquez | F10: REQ | G10: Revision de Plugins VZOR | H10: Ajuste de umbrales y monitoreos / escalamientos con VZOR
B11: 45891 | C11: 45870 | D11: NOC IPS | E11: Cristián Vásquez | F11: REQ | G11: Revision de respaldos VeeamBackup | H11: Revisión del resultado del JOB y tomar acciones si corresponde
B12: 45891 | C12: 45870 | D12: NOC IPS | E12: Cristián Vásquez | F12: REQ | G12: Revision de alertas VZOR | H12: Chequeo diario de alertas en herramienta VZOR
B13: 45891 | C13: 45870 | D13: NOC IPS | E13: Cristián Vásquez | F13: REQ | G13: Revision de servidores | H13: Configuración y ajustes de monitoreo
... B653: 46091 | C653: 46082 | D653: NOC IPS | E653: Cristián Vásquez | F653: REQ | G653: Envio informe mensual monitoreo | H653: Envio informe mensual monitoreo VZOR con incidentes e inventario
B654: 46092 | C654: 46082 | D654: NOC IPS | E654: Cristián Vásquez | F654: REQ | G654: Revision de respaldos VeeamBackup | H654: Revisión del resultado del JOB y tomar acciones si corresponde | I654: Finalizado | J654: 1
B655: 46092 | C655: 46082 | D655: NOC IPS | E655: Cristián Vásquez | F655: REQ | G655: Revision de alertas VZOR | H655: Chequeo diario de alertas en herramienta VZOR | I655: Finalizado | J655: 4
B656: 46092 | C656: 46082 | D656: NOC IPS | E656: Cristián Vásquez | F656: REQ | G656: Revision de Plugins VZOR | H656: Ajuste de umbrales y monitoreos / escalamientos con VZOR | I656: Finalizado | J656: 4
B657: 46092 | C657: 46082 | D657: NOC IPS | E657: Cristián Vásquez | F657: REQ | G657: Revision de servidores | H657: Configuración y ajustes de monitoreo | I657: Finalizado | J657: 2
B658: 46093 | C658: 46082 | D658: NOC IPS | E658: Cristián Vásquez | F658: REQ | G658: Revision de respaldos VeeamBackup | H658: Revisión del resultado del JOB y tomar acciones si corresponde | I658: Finalizado | J658: 1
B659: 46093 | C659: 46082 | D659: NOC IPS | E659: Cristián Vásquez | F659: REQ | G659: Revision de alertas VZOR | H659: Chequeo diario de alertas en herramienta VZOR | I659: Finalizado | J659: 4
B660: 46093 | C660: 46082 | D660: NOC IPS | E660: Cristián Vásquez | F660: REQ | G660: Revision de Plugins VZOR | H660: Ajuste de umbrales y monitoreos / escalamientos con VZOR | I660: Finalizado | J660: 4
B661: 46093 | C661: 46082 | D661: NOC IPS | E661: Cristián Vásquez | F661: REQ | G661: Revision de servidores | H661: Configuración y ajustes de monitoreo | I661: Finalizado | J661: 2
B662: 46094 | C662: 46082 | D662: NOC IPS | E662: Cristián Vásquez | F662: REQ | G662: Revision de respaldos VeeamBackup | H662: Revisión del resultado del JOB y tomar acciones si corresponde | I662: Finalizado | J662: 1
B663: 46094 | C663: 46082 | D663: NOC IPS | E663: Cristián Vásquez | F663: REQ | G663: Revision de alertas VZOR | H663: Chequeo diario de alertas en herramienta VZOR | I663: Finalizado | J663: 4
B664: 46094 | C664: 46082 | D664: NOC IPS | E664: Cristián Vásquez | F664: REQ | G664: Revision de Plugins VZOR | H664: Ajuste de umbrales y monitoreos / escalamientos con VZOR | I664: Finalizado | J664: 4
B665: 46094 | C665: 46082 | D665: NOC IPS | E665: Cristián Vásquez | F665: REQ | G665: Revision de servidores | H665: Configuración y ajustes de monitoreo | I665: Finalizado | J665: 2
... B724: 46108 | C724: 46082 | D724: NOC IPS | E724: Cristián Vásquez | F724: REQ | G724: Revision de servidores | H724: Configuración y ajustes de monitoreo | I724: Finalizado | J724: 2

Sheet AlejandroIpinza
B1: FECHA SOLICITUD | C1: Periodo | D1: AREA / PERSONAL SOLICITANTE | E1: PROFESIONAL | F1: INC / REQ / WARNING | G1: Actividad | H1: Detalle / Observación | I1: Estado (en proceso, pendiente, finalizado) | J1: Tiempo estimado actividad
B2: 45735 | C2: 45717 | D2: NOC IPS | E2: Alejandro Ipinza | F2: REQ | G2: Revision de respados VeeamBackup | H2: Revision del resultado del JOB y tomar acciones si corresponde
B3: 45735 | C3: 45717 | D3: NOC IPS | E3: Alejandro Ipinza | F3: REQ | G3: Revision de alertas VZOR | H3: Checheo diario de alertas en herramienta VZOR
B4: 45735 | C4: 45717 | D4: NOC IPS | E4: Alejandro Ipinza | F4: REQ | G4: Revision de Plugins VZOR | H4: Ajuste de umbrales y monitoreos / escalamientos con VZOR
B5: 45735 | C5: 45717 | D5: NOC IPS | E5: Alejandro Ipinza | F5: REQ | G5: Revision de servidores | H5: Configuracion y ajustes de monitoreo
B6: 45736 | C6: 45717 | D6: NOC IPS | E6: Alejandro Ipinza | F6: REQ | G6: Revision de respados VeeamBackup | H6: Revision del resultado del JOB y tomar acciones si corresponde
B7: 45736 | C7: 45717 | D7: NOC IPS | E7: Alejandro Ipinza | F7: REQ | G7: Revision de alertas VZOR | H7: Checheo diario de alertas en herramienta VZOR
B8: 45736 | C8: 45717 | D8: NOC IPS | E8: Alejandro Ipinza | F8: REQ | G8: Revision de Plugins VZOR | H8: Ajuste de umbrales y monitoreos / escalamientos con VZOR
B9: 45736 | C9: 45717 | D9: NOC IPS | E9: Alejandro Ipinza | F9: REQ | G9: Revision de servidores | H9: Configuracion y ajustes de monitoreo
B10: 45737 | C10: 45717 | D10: NOC IPS | E10: Alejandro Ipinza | F10: REQ | G10: Revision de respados VeeamBackup | H10: Revision del resultado del JOB y tomar acciones si corresponde
B11: 45737 | C11: 45717 | D11: NOC IPS | E11: Alejandro Ipinza | F11: REQ | G11: Revision de alertas VZOR | H11: Checheo diario de alertas en herramienta VZOR
B12: 45737 | C12: 45717 | D12: NOC IPS | E12: Alejandro Ipinza | F12: REQ | G12: Revision de Plugins VZOR | H12: Ajuste de umbrales y monitoreos / escalamientos con VZOR
B13: 45737 | C13: 45717 | D13: NOC IPS | E13: Alejandro Ipinza | F13: REQ | G13: Revision de servidores | H13: Configuracion y ajustes de monitoreo
... B416: 45880 | C416: 45870 | D416: NOC IPS | E416: Alejandro Ipinza | F416: INC | G416: Configuracion snmp servidor windows | H416: configuración snmp en el servidor DC06 / 10.210.3.219
